Workbook

Sheet TEST_NYC_Coding
A1: NYC Coding — GenAI Policy Coding
A4: ID | B4: Tier | C4: Region | D4: Jurisdiction / Institution | E4: Institution | F4: Document Title | G4: Document Type | H4: Publication Date | I4: Source URL | J4: Stance | K4: Disclosure | L4: Discretion | M4: Focus (Primary) | N4: Focus (Secondary) | O4: Enforcement | P4: Coverage | Q4: Key Quote (verbatim) | R4: Coder Notes | S4: Coder | T4: Date Coded | U4: Coder Agreement (Initials if agree and DONT AGREE)
A5: NYC-001 | B5: National/Federal | C5: NYC | D5: U.S. Office of Management and Budget | F5: OMB M-25-21: Accelerating Federal Use of AI through Innovation, Governance, and Public Trust | G5: Official Guidance | H5: 45750 | I5: https://www.whitehouse.gov/wp-content/uploads/2025/02/M-25-21-Accelerating-Federal-Use-of-AI-through-Innovation-Governance-and-Public-Trust.pdf | J5: Functional | K5: Not specified | L5: Gov-mandated | M5: Privacy/Data/Ethics | N5: Professional Readiness | O5: Guidance only | P5: All community | Q5: “Agencies are directed to accelerate the Federal use of AI by focusing on three key priorities: innovation, governance, and public trust.” | S5: EY | T5: 46141
A6: NYC-002 | B6: National/Federal | C6: NYC | D6: U.S. Department of Education | F6: U.S. Department of Education Dear Colleague Letter on AI and Education Outcomes | G6: Official Guidance | H6: 45860 | I6: https://www.ed.gov/media/document/opepd-ai-dear-colleague-letter-7222025-110427.pdf | J6: Encouraging | K6: Not specified | L6: Hybrid/Mixed | M6: Pedagogy/Learning | N6: AI Literacy | O6: Guidance only | P6: Both | Q6: “The Department encourages grantees to explore how AI can enhance teaching and learning, expand access, and support educators, without replacing the critical role they play.” | S6: EY | T6: 46141
A7: NYC-003 | B7: National/Federal | C7: NYC | D7: U.S. Federal Government | F7: Removing Barriers to American Leadership in Artificial Intelligence | G7: Executive Order | H7: 45680 | I7: https://www.whitehouse.gov/presidential-actions/2025/01/removing-barriers-to-american-leadership-in-artificial-intelligence/ | J7: Encouraging | K7: Not specified | L7: Gov-mandated | M7: Professional Readiness | N7: AI Literacy | O7: Guidance only | P7: All community | Q7: "It is the policy of the United States to sustain and enhance America’s global AI dominance in order to promote human flourishing, economic competitiveness, and national security." | S7: EY | T7: 46137
A8: NYC-004 | B8: National/Federal | C8: NYC | D8: U.S. Department of Education | F8: Artificial Intelligence and the Future of Teaching and Learning | G8: Official Guidance | H8: 45047 | I8: https://www.ed.gov/sites/ed/files/documents/ai-report/ai-report.pdf | J8: Cautious | K8: Recommended | L8: Not specified | M8: Pedagogy/Learning | N8: Equity | O8: Guidance only | P8: All community | Q8: "In summary, it is imperative to address AI in education now to realize key opportunities, prevent and mitigate emergent risks, and tackle unintended consequences." | S8: EY | T8: 46137
A9: NYC-005 | B9: National/Federal | C9: NYC | D9: National Institute of Standards and Technology (NIST) | F9: Artificial Intelligence Risk Management Framework: Generative Artificial Intelligence Profile | G9: Official Guidance | H9: 45499 | I9: https://doi.org/10.6028/NIST.AI.600-1 | J9: Cautious | K9: Recommended | L9: Not specified | M9: Privacy/Data/Ethics | N9: AI Literacy | O9: Guidance only | P9: All community | Q9: "This document defines risks that are novel to or exacerbated by the use of GAI. After introducing and describing these risks, the document provides a set of suggested actions to help organizations govern, map, measure, and manage these risks." | R9: This document has a multilevel analysis of different aspects of Gen AI, the key quote might not be enough to summarize all the ideas in the document. | S9: EY | T9: 46137
A10: NYC-006 | B10: State/Territory | C10: NYC | D10: Office of the State Comptroller; Division of State Government Accountability | F10: New York State Artificial Intelligence Governance Audit | G10: Other | H10: 45750 | I10: https://www.osc.ny.gov/state-agencies/audits/2025/04/03/new-york-state-artificial-intelligence-governance?utm_source=chatgpt.com | J10: Cautious | K10: Recommended | L10: Not specified | M10: Privacy/Data/Ethics | N10: AI Literacy | O10: Guidance only | P10: All community | Q10: NYS does not have an effective AI governance framework. While the AI Policy outlines certain requirements or recommendations for agencies to consider, it lacks adequate guidance and procedures on how these agencies can meet these expectations. | S10: EY | T10: 46137
A11: NYC-007 | B11: State/Territory | C11: NYC | D11: New York City Office of Technology and Innovation (OTI) | F11: AI Public Participation & Engagement Guidance | G11: Official Guidance | H11: 46006 | I11: https://www.nyc.gov/assets/oti/downloads/pdf/NYC-OTI_Guidance_AI-Public-Participation-and-Engagement.pdf | J11: Cautious | K11: Recommended | L11: Hybrid/Mixed | M11: Equity | N11: Privacy/Data/Ethics | O11: Guidance only | P11: All community | Q11: "As AI tools are increasingly used and incorporated into agencies’ existing software and systems, a careful consideration of varied real or potential public impacts will be critical. Agencies should seek to integrate meaningful public participation and engagement, where appropriate, to understand these impacts, mitigate risk, support trust and transparency, and facilitate successful development and roll-out that serves the needs and interests of New Yorkers." | S11: EY | T11: 46137
A12: NYC-008 | B12: State/Territory | C12: NYC | D12: New York City Office of Technology and Innovation (OTI) | F12: NYC Use Guidance: Generative Artificial Intelligence | G12: Official Guidance | H12: 46021 | I12: https://www.nyc.gov/assets/oti/downloads/pdf/New-York-City-Generative-AI-Use-Guidance.pdf | J12: Cautious | K12: Required | L12: Hybrid/Mixed | M12: Privacy/Data/Ethics | N12: AI Literacy | O12: Guidance only | P12: All community | Q12: "The City is committed to a responsible approach to emerging technologies. This Use Guidance provides a framework for the responsible use of GenAI by City personnel, aligned with the City’s AI Principles, and applicable laws and policies." | S12: EY | T12: 46137
A13: NYC-009 | B13: State/Territory | C13: NYC | D13: New York State Office of Information Technology Services (ITS) | F13: NYS ITS Acceptable Use of Artificial Intelligence Technologies | G13: Official Guidance | H13: 45292 | I13: https://its.ny.gov/system/files/documents/2026/01/nys-p24-001-acceptable-use-of-ai.pdf | J13: Cautious | K13: Required | L13: Hybrid/Mixed | M13: Privacy/Data/Ethics | N13: Equity | O13: Guidance only | P13: All community | Q13: "Through the responsible use of AI, SEs can drive innovation, increase operational efficiencies, and better serve New Yorkers while protecting privacy, managing risk, and promoting accountability, safety, and equity. Agencies are encouraged to responsibly adopt AI technologies and should consider this policy a tool to aid in that adoption." | S13: EY | T13: 46137
A14: NYC-010 | B14: Institutional | C14: NYC | D14: Columbia University | E14: Columbia | F14: Generative AI Policy (Office of the Provost) | G14: University Policy | H14: 2025 | I14: https://provost.columbia.edu/content/office-senior-vice-provost/ai-policy | J14: Cautious | K14: Required | L14: Hybrid/Mixed | M14: Academic Integrity | N14: Privacy/Data/Ethics | O14: Referenced to integrity code | P14: Both | Q14: "Generative AI tools have the capacity to expedite existing processes and make possible new ones. These tools also have the potential to foster student learning and advance many aspects of research and health care delivery. While the University supports the responsible use of AI, these novel tools have notable limitations and present new risks that must be taken into consideration when using these technologies." | S14: EY | T14: 46137
A15: NYC-011 | B15: Institutional | C15: NYC | D15: Columbia University | E15: Columbia | F15: Best Practices for Responsible AI Use | G15: University Policy | H15: 46031 | I15: https://etc.cuit.columbia.edu/news/best-practices-responsible-ai-use | J15: Functional | K15: Conditional | L15: Instructor decides | M15: Privacy/Data/Ethics | N15: AI Literacy | O15: Guidance only | P15: Both | Q15: CUIT’s guidance is designed to help the Columbia community benefit from AI while avoiding common failure points, particularly when institutional or sensitive data is involved.
A16: NYC-012 | B16: Institutional | C16: NYC | D16: New York University | E16: NYU | F16: Teaching with Generative AI — NYU FAQ | G16: University Policy | H16: 45708 | I16: https://www.nyu.edu/faculty/teaching-and-learning-resources/teaching-with-generative-tools/frequently-asked-questions.html | J16: Functional | K16: Recommended | L16: Instructor decides | M16: Pedagogy/Learning | N16: Academic Integrity | O16: Explicit penalties | P16: Faculty only | Q16: "Generative AI is a new arrival in the academic environment and can be used in a wide variety of ways. Because of this novelty and flexibility, there are few standard approaches to its use beyond an Faculty/Inst. decides restriction on taking credit for AI output without acknowledging its use. Most policies will be set by the schools or by individual faculty members." | S16: EY | T16: 46137
A17: NYC-013 | B17: Faculty/School | C17: NYC | D17: New York University | E17: NYU | F17: Academic Integrity and Syllabus Support in the Age of Generative AI | G17: University Policy | H17: 2025 | I17: https://steinhardt.nyu.edu/faculty-and-staff/academic-affairs/steinhardt-ai-hub/academic-integrity-and-syllabus-support-age | J17: Functional | K17: Recommended | L17: Instructor decides | M17: Academic Integrity | N17: Pedagogy/Learning | O17: Referenced to integrity code | P17: Faculty only | Q17: "Creating clear policies around AI use is essential to maintaining academic integrity and setting student expectations. These policies should outline when and how AI tools like ChatGPT, Perplexity.ai, or Grammarly can be used and ensure students understand the ethical implications of AI in academic work." | S17: EY | T17: 46137
A18: NYC-014 | B18: Faculty/School | C18: NYC | D18: New York University (Stern) | E18: NYU | F18: Teaching and Learning with Generative AI at NYU Stern | G18: Library Guide | I18: https://sites.google.com/stern.nyu.edu/teaching-learning-gen-ai/home | J18: Functional | K18: Recommended | L18: Instructor decides | M18: AI Literacy | N18: Pedagogy/Learning | O18: Referenced to integrity code | P18: Both | Q18: “This resource was created by the Learning Science Lab to support the NYU Stern community in thinking deliberately about the use of generative AI (genAI) and other related technologies as they arise.” | S18: EY | T18: 46137
A19: NYC-015 | B19: Faculty/School | C19: NYC | D19: New York University (Tisch School of the Arts) | E19: NYU | F19: Tisch Academic Integrity | G19: University Policy | H19: 2026 | I19: https://tisch.nyu.edu/faculty/academic-integ | J19: Cautious | K19: Not specified | L19: Instructor decides | M19: Academic Integrity | N19: Pedagogy/Learning | O19: Explicit penalties | P19: Both | Q19: Generative AI: Please note, with recent developments in technologies like ChatGPT, the existence of a well-written paragraph is no longer evidence of human effort. To read the Provost's notes on how to adapt writing assignments in the age of generative AI, click here. | S19: EY | T19: 46143
A20: NYC-016 | B20: Faculty/School | C20: NYC | D20: New York University (Tisch School of the Arts Provost) | E20: NYU | F20: Adapting Writing Assignments to Generative AI | G20: FAQ/Resource Page | I20: https://docs.google.com/document/d/1CbWKCBCMuO1kJlsK-ukD5lXGVuKuSzq8H8MFAQVvdDM/edit?usp=sharing | J20: Functional | K20: Recommended | L20: Instructor decides | M20: AI Literacy | N20: Academic Integrity | O20: Referenced to integrity code | P20: Faculty only | Q20: Even if an instructor does not intend to change individual assignments, the availability and generality of these tools increases the need for clarity around the instructor’s expectations. Whatever strategies an instructor might adopt for individual assignments or a whole course, instructors should explain to students what is expected around AI use. | S20: EY | T20: 46143
A21: NYC-017 | B21: Institutional | C21: NYC | D21: City University of New York (CUNY) | E21: CUNY | F21: CUNY AI Academic Hub (General) | G21: University Policy | H21: 2025 | I21: https://www.cuny.edu/academics/ai-academic-hub/ | J21: Encouraging | K21: Not specified | L21: Not specified | M21: AI Literacy | N21: Professional Readiness | O21: Guidance only | P21: Both | Q21: "Our Vision is shaping the Future of Human-AI Powered Education. CUNY is at the forefront of AI-driven transformation in higher education. Our mission is to harness AI’s potential to empower learning, drive research, and foster innovation—ensuring equitable opportunities for all." | S21: EY | T21: 46137
A22: NYC-018 | B22: Faculty/School | C22: NYC | D22: Baruch College (CUNY) | E22: CUNY | F22: Guidelines for AI Use at Baruch College | G22: University Policy | H22: 45888 | I22: https://provost.baruch.cuny.edu/artificial-intelligence-think-tank/ai-use-guidance/ | J22: Encouraging | K22: Required | L22: Instructor decides | M22: Pedagogy/Learning | N22: Privacy/Data/Ethics | O22: Referenced to integrity code | P22: Both | Q22: "Faculty are encouraged to integrate artificial intelligence education into their courses as appropriate to their disciplines, but are not obligated to do so. All syllabi should include a course- and discipline-appropriate policy on the use of generative AI." | S22: EY | T22: 46138
A23: NYC-019 | B23: Faculty/School | C23: NYC | D23: Kingsborough Community College (CUNY) | E23: CUNY | F23: Kingsborough Community College Academic Integrity Policy | G23: University Policy | H23: 2025 | I23: https://www.kbcc.cuny.edu/studentaffairs/student_conduct/academic_integrity.html | J23: Cautious | K23: Required | L23: Faculty/Inst. decides | M23: Academic Integrity | N23: Equity | O23: Referenced to integrity code | P23: Students only | Q23: "Example of cheating include: (...) Submitting content generated by another person or an AI tool or any other source as solely your own work as your own, including, but not limited to, material obtained in whole or in part from commercial study or homework help websites, or content generated or altered by AI or digital paraphrasing tools without proper citation." | S23: EY | T23: 46137
A24: NYC-020 | B24: Institutional | C24: NYC | D24: The City College of New York (CUNY) | E24: CUNY | F24: AI Across CUNY | G24: University Policy | H24: 2025 | I24: https://www.ccny.cuny.edu/tlc/making-your-course-available?srsltid=AfmBOoojIHHL2OxDCdrK-0Xc9elMyrAnNWVcOtEzwybtMdTvH4Pbcfy- | J24: Functional | K24: Required | L24: Instructor decides | M24: AI Literacy | N24: Pedagogy/Learning | O24: Referenced to integrity code | P24: Both | Q24: "Our goal is to provide a collaborative space for sharing effective strategies for the responsible and critical use of AI, particularly within the CUNY community." | S24: EY | T24: 46137
A25: NYC-021 | B25: Faculty/School | C25: NYC | D25: Hunter College (CUNY) | E25: CUNY | F25: CUNY Academic Integrity Policy | G25: University Policy | I25: https://www.hunter.cuny.edu/center-for-digital-learning-and-innovative-pedagogy/online-learning-resources/academic-integrity-policy/ | J25: Cautious | K25: Required | L25: Instructor decides | M25: Academic Integrity | N25: Professional Readiness | O25: Explicit penalties | P25: Both | Q25: Preparing students to learn from and use AI responsibly and ethically is critical to the University’s mission, to ensuring academic integrity, to securing the rigor of the University’s academic programs. Further, students must become facile with the use of AI to learn effectively in today’s world and to prepare for their AI-assisted careers and lives in the future. | S25: EY | T25: 46143
A26: NYC-022 | B26: Faculty/School | C26: NYC | D26: Queens College (CUNY) | E26: CUNY | F26: Generative AI in the Classroom: Best Practices, a CETLL Guide | G26: FAQ/Resource Page | H26: 45717 | I26: https://www.qc.cuny.edu/cetll/wp-content/uploads/sites/138/2026/03/Generative-AI-in-the-Classroom-Best-Practices-a-CETLL-Guide_ACCESSIBLE_3.19.pdf | J26: Functional | K26: Recommended | L26: Instructor decides | M26: Pedagogy/Learning | N26: AI Literacy | O26: Guidance only | P26: Faculty only | Q26: Currently, there is no specific CUNY or QC policy on the use of artificial intelligence in the classroom outside of mentions of AI in the CUNY Academic Integrity Policy. This means that, as instructors, we have a lot of flexibility and responsibility to consider how and when the use of generative AI is acceptable in our classes to clearly communicate these parameters to our students as we prepare them for the integration of these technologies in work and life.
A27: NYC-023 | B27: Faculty/School | C27: NYC | D27: Teachers College, Columbia University | E27: Columbia | F27: Recommendations for Generative AI Use for teaching at TC | G27: FAQ/Resource Page | H27: 2025 | I27: https://www.tc.columbia.edu/digitalfuturesinstitute/ai-in-education/recommendations-for-generative-ai-use-at-tc/ | J27: Functional | K27: Conditional | L27: Instructor decides | M27: Pedagogy/Learning | N27: Academic Integrity | O27: Referenced to integrity code | P27: Both | Q27: "TC provides flexibility for instructors to experiment with and use generative AI in their courses. Each TC instructor should set specific policies about student use of generative AI for their course assignments" | S27: EY | T27: 46137
A28: NYC-024 | B28: Course-wide | C28: NYC | D28: Columbia Course 1 | E28: Columbia | F28: CSEE 4119: Introduction to Computer Networks | G28: Syllabus | H28: Fall 2025 | I28: CSEE 4119_ An Introduction to Computer Networks (Fall 2025).pdf | J28: Prohibitive | K28: Not specified | L28: Instructor decides | M28: Academic Integrity | N28: Pedagogy/Learning | O28: Explicit penalties | P28: Students only | Q28: "The use of ChatGPT or any other generative artificial intelligence (AI) tools at any stage of the work process, including preliminary stages, is strictly prohibited. Violations of this policy will be considered academic misconduct." | S28: EY | T28: 46137 | U28: YM
A29: NYC-025 | B29: Course-wide | C29: NYC | D29: Columbia Course 2 | E29: Columbia | F29: PSYC UN1610: Intro to Statistics for Behavioral Scientists | G29: Syllabus | H29: Fall 2025 | I29: Fall 2025 Syllabus UN1610 Fox-Glassman Statistics for Behavioral Scientists.pdf | J29: Prohibitive | K29: Not specified | L29: Instructor decides | M29: Pedagogy/Learning | N29: Academic Integrity | O29: Explicit penalties | P29: Students only | Q29: "“Doing your own work” means making at attempt at each problem without the support of AI. There are lots of tools that can do stats problems for you. You will do best in this course if you use these only for checking your work; you will have a very bad time if you regularly replace the process of learning the material with a tendency to let AI tell you the answer." | S29: EY | T29: 46137
A30: NYC-026 | B30: Course-wide | C30: NYC | D30: Columbia Course 3 | E30: Columbia | F30: COMS 4705: Natural Language Processing | G30: Syllabus | H30: Fall 2025 | I30: COMS 4705_ Natural Language Processing.pdf | J30: Encouraging | K30: Not specified | L30: Instructor decides | M30: Professional Readiness | N30: AI Literacy | O30: Referenced to integrity code | P30: Students only | Q30: "AI tools (e.g., ChatGPT, Cursor, Claude Code) are fully allowed for Assignments 1–4. While I recommend doing the assignments on your own (or with minimal AI hints) as prep for exams, you may use AI to fully solve them if you wish." | S30: EY | T30: 46137
A31: NYC-027 | B31: Course-wide | C31: NYC | D31: Columbia/TC Course 4 | E31: Columbia | F31: HUDK 4051 Learning Analytics: Process and Theory | G31: Syllabus | H31: Summer 2024 | I31: HUDK4051_Sp26_Syllabus_Yu.pdf | J31: Encouraging | K31: Required | L31: Instructor decides | M31: Professional Readiness | N31: AI Literacy | O31: Referenced to integrity code | P31: Students only | Q31: "Generative AI tools are encouraged in this course for research and completion of assignments, provided that all AI-generated content is clearly attributed as such in the student’s work." | S31: EY | T31: 46137
A32: NYC-028 | B32: Course-wide | C32: NYC | D32: Columbia Course 5 | E32: Columbia | F32: COMS 4160: Introduction to Computer Graphics | G32: Syllabus | H32: Fall 2025 | I32: COMS 4160 — Introduction to Computer Graphics (Fall 2025).pdf | J32: Functional | K32: Conditional | L32: Instructor decides | M32: Academic Integrity | N32: Pedagogy/Learning | O32: Referenced to integrity code | P32: Students only | Q32: “You should not use generative AI to produce the solution to any of the assignments. You are allowed to use generative AI to produce your final project image (but do not lie about it if asked).”
A33: NYC-029 | B33: Course-wide | C33: NYC | D33: Columbia Course 6 | E33: Columbia | F33: Generative AI for Business | G33: Syllabus | H33: Fall 2025 | I33: olivier toubia - B8609 Generative AI for Business Fall 2025 Toubia.pdf | J33: Functional | K33: Required | L33: Instructor decides | M33: AI Literacy | N33: Academic Integrity | O33: Referenced to integrity code | P33: Students only | Q33: “You will use Generative AI tools for your work in this course. When you use any of these tools to complete assignments, you must describe how you used them to generate your response to the assignment.”
A34: NYC-030 | B34: Course-wide | C34: NYC | D34: NYU Course 1 | E34: NYU | F34: Programming & Algorithms using Python - Stern | G34: Syllabus | H34: Fall 2025 | I34: 2025Programming_in_Python_Software_DevSosulski (1).pdf | J34: Functional | K34: Required | L34: Instructor decides | M34: Professional Readiness | N34: Pedagogy/Learning | O34: Referenced to integrity code | P34: Students only | Q34: "Large language models (LLMS) may be used in this class, however you must cite it as you would any other reference material. Failure to acknowledge that content was GenAI generated will be considered a violation of academic integrity." | S34: EY | T34: 46137
A35: NYC-031 | B35: Course-wide | C35: NYC | D35: NYU Course 2 | E35: NYU | F35: Global Strategy - Stern | G35: Syllabus | H35: Fall 2025 | I35: MGMT-GB.2340_10_F2026.pdf | J35: Prohibitive | K35: Required | L35: Instructor decides | M35: Pedagogy/Learning | N35: Academic Integrity | O35: Explicit penalties | P35: Students only | Q35: "Your thoughts, opinions, and personal experiences are integral part of the learning process. As such, the use of generative AI is prohibited in this class. In this class, students are to engage in authentic self-reflection and genuine thinking." | S35: EY | T35: 46137 | U35: cy
A36: NYC-032 | B36: Course-wide | C36: NYC | D36: NYU Course 3 | E36: NYU | F36: Tax Policy Seminar - NYU Law | G36: Syllabus | H36: Spring 2026 | I36: Tax Policy Seminar Syllabus NYU Spring 2026_2DF65D21-D8A0-861C-BF9EDC4A13E27F5A.pdf | J36: Encouraging | K36: Required | L36: Instructor decides | M36: Academic Integrity | N36: Pedagogy/Learning | O36: Referenced to integrity code | P36: Students only | Q36: "That being said, for purposes of this course, for the response papers (only), the use of large language models/generative AI is expressly permitted as long as (a) you put in red font any material generated by AI; (b) you check any AI-generated content and take full responsibility for it as your written work product; and (c) you disclose and describe your use of AI with a general prefatory note or footnote indicating what background material you provided to the large language model, what prompts you used, and any revisions you made to AI-generated content." | S36: EY | T36: 46137 | U36: cy
A37: NYC-033 | B37: Course-wide | C37: NYC | D37: NYU Course 4 | E37: NYU | F37: Environmental Justice Seminar - NYU Law | G37: Syllabus | H37: Spring 2026 | I37: Early syllabus Spring 2026_33DBB621-E564-129B-AD1D4CB561DDC5F8.pdfg | J37: Cautious | K37: Not specified | L37: Instructor decides | M37: Pedagogy/Learning | N37: Academic Integrity | O37: Guidance only | P37: Students only | Q37: "Students should not use ChatGPT or other generative AI tools as a shortcut or substitute for coming up with their own answers to the prompts. Use of AI tools to help gather information should be done with caution." | S37: EY | T37: 46137
A38: NYC-034 | B38: Course-wide | C38: NYC | D38: NYU Course 5 | E38: NYU | F38: ENVIRONMENTAL JUSTICE SEMINAR | G38: Syllabus | H38: Spring 2026 | I38: ENVIRONMENTAL JUSTICE SEMINAR.pdf | J38: Cautious | K38: Not specified | L38: Instructor decides | M38: Pedagogy/Learning | N38: Academic Integrity | O38: Guidance only | P38: Students only | Q38: In this assignment, we are expecting students to think critically about the issues on their own and in collaboration with their group members. Students should not use ChatGPT or other generative AI tools as a shortcut or substitute for coming up with their own answers to the prompts. Use of AI tools to help gather information should be done with caution.
A39: NYC-035 | B39: Course-wide | C39: NYC | D39: NYU Course 6 | E39: NYU | F39: Foundations of FinTech | G39: Syllabus | H39: Fall 2024 | I39: 2024FoF-Fall2024-Sec10-syllabus-2024-10-10.pdf | J39: Functional | K39: Required | L39: Instructor decides | M39: Academic Integrity | N39: Pedagogy/Learning | O39: Explicit penalties | P39: Students only | Q39: “You can use AI at your own risk, but you are responsible for the accuracy and integrity of anything that you submit.”
A40: NYC-036 | B40: Course-wide | C40: NYC | D40: CUNY — Course 1 | E40: CUNY | F40: MATH 190: College Algebra | G40: Syllabus | H40: 2025 | I40: Syllabus_190.pdf | J40: Functional | K40: Required | L40: Instructor decides | M40: Pedagogy/Learning | N40: Academic Integrity | O40: Referenced to integrity code | P40: Students only | Q40: "You may use generative AI tools (such as ChatGPT) to assist with homework in this course, provided you clearly indicate when and how AI was used, including the specific tool and model. All submitted work must reect your own understandingyou are responsible for checking and explaining any AI-assisted solutions." | S40: EY | T40: 46137 | U40: cy
A41: NYC-037 | B41: Course-wide | C41: NYC | D41: CUNY — Course 2 | E41: CUNY | F41: ENV 3070: Agroecology | G41: Syllabus | H41: Fall 2025 | I41: viewcontent.pdf | J41: Functional | K41: Required | L41: Instructor decides | M41: Pedagogy/Learning | N41: Academic Integrity | O41: Referenced to integrity code | P41: Students only | Q41: "Use of generative AI tools (e.g. ChatGPT) is allowed. For each written assignment where generative AI is employed, you must include a cover letter describing what tool(s) you used, how you used it, why it was useful, and any shortcomings or limitations you encountered." | S41: EY | T41: 46137
A42: NYC-038 | B42: Course-wide | C42: NYC | D42: CUNY — Course 3 | E42: CUNY | F42: Psychology 32: Human Growth and Development | G42: Syllabus | H42: 2025 | I42: Psych32.pdf | J42: Functional | K42: Required | L42: Instructor decides | M42: Pedagogy/Learning | N42: Academic Integrity | O42: Referenced to integrity code | P42: Students only | Q42: "The use of generative AI tools is permitted in this course for the following activities: Brainstorming and researching; Drafting an outline; Organizing your thoughts; Checking grammar. Please cite the AI tool you use, if used. Please share the date of access and the specific prompt or query you used to generate the output received by AI" | S42: EY | T42: 46137 | U42: cy
A43: NYC-039 | B43: Course-wide | C43: NYC | D43: CUNY — Course 4 | E43: CUNY | F43: BBA 313: Foundations of Entrepreneurship | G43: Syllabus | H43: Spring 2026 | I43: BBA 313 - Foundations of Entrepreneurship.pdf | J43: Encouraging | K43: Required | L43: Hybrid/Mixed | M43: Academic Integrity | N43: Professional Readiness | O43: Referenced to integrity code | P43: Students only | Q43: "The syllabus references CUNY’s updated academic integrity policy addressing GenAI tools such as ChatGPT and Copilot." | S43: EY | T43: 46137
A44: NYC-040 | B44: Course-wide | C44: NYC | D44: CUNY — Course 5 | E44: CUNY | F44: FNES 722 EXERCISE, ENERGY BALANCE, AND BODY COMPOSITION | G44: Syllabus | H44: Spring 2026 | I44: FNES 722 EXERCISE ENERGY BALANCE AND BODY COMPOSITION.pdf | J44: Cautious | K44: Required | L44: Instructor decides | M44: Academic Integrity | N44: Pedagogy/Learning | O44: Explicit penalties | P44: Students only | Q44: “Using artificial intelligence tools to generate content for assignments or exams, including but not limited to language models or code generators, without written authorization from the instructor.” | U44: cy

Sheet NEW_NYC_Coding
A1: NYC Coding — GenAI Policy Coding
A4: ID | B4: Tier | C4: Region | D4: Jurisdiction / Institution | E4: Institution | F4: Document Title | G4: Document Type | H4: Publication Date | I4: Source URL | J4: Stance | K4: Disclosure | L4: Discretion | M4: Focus (Primary) | N4: Focus (Secondary) | O4: Enforcement | P4: Coverage | Q4: Key Quote (verbatim) | R4: Coder Notes | S4: Coder | T4: Date Coded | U4: Coder Agreement (Initials if agree and Comment if disagree)
A5: NYC-001 | B5: National/Federal | C5: NYC | D5: US Federal (White House) | F5: National Policy Framework for Artificial Intelligence | G5: Executive Order | H5: 46376 | I5: https://www.whitehouse.gov/wp-content/uploads/2026/03/03.20.26-National-Policy-Framework-for-Artificial-Intelligence-Legislative-Recommendations.pdf | J5: Functional | K5: Not specified | L5: Gov-mandated | M5: Professional Readiness | N5: AI Literacy | O5: Guidance only | P5: Whole community | Q5: “The federal government must establish a federal AI policy framework to protect American rights, support innovation, and prevent a fragmented patchwork of state regulations.” | S5: EY | T5: 46157 | V5: {=XLOOKUP($I5,TEST_NYC_Coding!$I$5:$I$44,TEST_NYC_Coding!$A$5:$A$44,"")}
A6: NYC-002 | B6: National/Federal | C6: NYC | D6: US Federal (White House) | F6: Executive Order: Eliminating State Law Obstruction of National AI Policy | G6: Executive Order | H6: 45973 | I6: https://www.whitehouse.gov/presidential-actions/2025/12/eliminating-state-law-obstruction-of-national-artificial-intelligence-policy/ | J6: Encouraging | K6: Not specified | L6: Gov-mandated | M6: Professional Readiness | N6: AI Literacy | O6: Guidance only | P6: Whole community | Q6: It is the policy of the United States to sustain and enhance the United States’ global AI dominance through a minimally burdensome national policy framework for AI. | S6: EY | T6: 46157 | V6: {=XLOOKUP($I6,TEST_NYC_Coding!$I$5:$I$44,TEST_NYC_Coding!$A$5:$A$44,"")}
A7: NYC-003 | B7: National/Federal | C7: NYC | D7: ACUS (Administrative Conference of the United States) | F7: ACUS Policy on Use of Generative AI | G7: Law/Regulation | H7: 45942 | I7: https://www.acus.gov/sites/default/files/documents/ACUS_Policy_on_Use_of_GenAI-20251210.pdf | J7: Cautious | K7: Required | L7: Gov-mandated | M7: Privacy/Data/Ethics | N7: Academic Integrity | O7: Referenced to integrity code | P7: Whole community | Q7: Federal employees must disclose GenAI use and must not input sensitive or confidential information into public AI tools | S7: EY | T7: 46157 | V7: {=XLOOKUP($I7,TEST_NYC_Coding!$I$5:$I$44,TEST_NYC_Coding!$A$5:$A$44,"")}
A8: NYC-004 | B8: National/Federal | C8: NYC | D8: US Federal (White House) | F8: Advancing Artificial Intelligence Education for American Youth | G8: Executive Order | H8: 45770 | I8: https://www.whitehouse.gov/presidential-actions/2025/04/advancing-artificial-intelligence-education-for-american-youth/ | J8: Encouraging | K8: Not specified | L8: Gov-mandated | M8: Professional Readiness | N8: Pedagogy/Learning | O8: Guidance only | P8: Whole community | Q8: “It is the policy of the United States to promote AI literacy and proficiency among Americans by promoting the appropriate integration of AI into education, providing comprehensive AI training for educators, and fostering early exposure to AI concepts and technology to develop an AI-ready workforce and the next generation of American AI innovators.” | S8: EY | T8: 46157 | V8: {=XLOOKUP($I8,TEST_NYC_Coding!$I$5:$I$44,TEST_NYC_Coding!$A$5:$A$44,"")}
A9: NYC-005 | B9: National/Federal | C9: NYC | D9: US Federal (White House) | F9: Ensuring a National Policy Framework for AI | G9: Executive Order | H9: 46002 | I9: https://www.whitehouse.gov/presidential-actions/2025/12/eliminating-state-law-obstruction-of-national-artificial-intelligence-policy/ | J9: Encouraging | K9: Not specified | L9: Gov-mandated | M9: Professional Readiness | N9: Privacy/Data/Ethics | O9: Explicit penalties | P9: Whole community | Q9: “United States AI companies must be free to innovate without cumbersome regulation.” | S9: EY | T9: 46157 | V9: {=XLOOKUP($I9,TEST_NYC_Coding!$I$5:$I$44,TEST_NYC_Coding!$A$5:$A$44,"")}
A10: NYC-006 | B10: City/Territory | C10: NYC | D10: NYC — Office of Technology and Innovation (OTI) | E10: OTI | F10: NYC Use Guidance: Generative Artificial Intelligence | G10: Official Guidance | H10: 30/2/2025 | I10: https://www.nyc.gov/assets/oti/downloads/pdf/New-York-City-Generative-AI-Use-Guidance.pdf | J10: Cautious | K10: Required | L10: Gov-mandated | M10: Privacy/Data/Ethics | N10: AI Literacy | O10: Guidance only | P10: Whole community | Q10: "The City is committed to a responsible approach to emerging technologies. This Use Guidance provides a framework for the responsible use of GenAI by City personnel, aligned with the City’s AI Principles, and applicable laws and policies." | S10: EY | V10: {=XLOOKUP($I10,TEST_NYC_Coding!$I$5:$I$44,TEST_NYC_Coding!$A$5:$A$44,"")} -> NYC-008
A11: NYC-007 | B11: City/Territory | C11: NYC | D11: New York City — Office of Technology and Innovation (OTI), Strategic Initiatives Division | E11: OTI | F11: Preliminary Use Guidance: Generative Artificial Intelligence | G11: Official Guidance | H11: 45352 | I11: https://www.nyc.gov/assets/oti/downloads/pdf/about/preliminary-use-guidance-general-artificial-intelligence.pdf | J11: Cautious | K11: Required | L11: Gov-mandated | M11: Privacy/Data/Ethics | N11: AI Literacy | O11: Referenced to integrity code | P11: Whole community | Q11: In order to support critical engagement by end users and maintain public trust in city government, it is best practice to proactively disclose the use of Generative AI in all contexts | S11: EY | V11: {=XLOOKUP($I11,TEST_NYC_Coding!$I$5:$I$44,TEST_NYC_Coding!$A$5:$A$44,"")}
A12: NYC-008 | B12: City/Territory | C12: NYC | D12: NYC Office of Technology and Innovation | E12: OTI | F12: NYC Artificial Intelligence Action Plan | G12: Official Guidance | I12: https://www.nyc.gov/assets/oti/downloads/pdf/reports/artificial-intelligence-action-plan.pdf | J12: Cautious | K12: Not specified | L12: Gov-mandated | M12: Privacy/Data/Ethics | N12: AI Literacy | O12: Guidance only | P12: Whole community | Q12: “The NYC AI Action Plan introduces seven new initiatives… toward harnessing the power of AI to deliver positive outcomes for New Yorkers, while carefully mitigating the risks these technologies present.” | S12: EY | V12: {=XLOOKUP($I12,TEST_NYC_Coding!$I$5:$I$44,TEST_NYC_Coding!$A$5:$A$44,"")}
A13: NYC-009 | B13: City/Territory | C13: NYC | D13: NYC Office of Technology and Innovation | E13: OTI | F13: NYC AI Action Plan Annual Progress Report - 2025 | G13: Other | H13: 45946 | I13: https://www.nyc.gov/assets/oti/downloads/pdf/AI-Action-Plan-Progress-Report-Year-2.pdf | J13: Cautious | K13: Not specified | L13: Gov-mandated | M13: Privacy/Data/Ethics | N13: AI Literacy | O13: None stated | P13: Whole community | Q13: “The Action Plan included 37 actions across seven initiatives focused on supporting city agencies’ efforts to understand and use AI tools, fostering appropriate governance across the city…” | S13: EY | V13: {=XLOOKUP($I13,TEST_NYC_Coding!$I$5:$I$44,TEST_NYC_Coding!$A$5:$A$44,"")}
A14: NYC-010 | B14: City/Territory | C14: NYC | D14: NYC Public Schools | E14: NYCPS | F14: NYC Public Schools (NYCPS) AI Guidance | G14: Other | H14: 46082 | I14: https://www.schools.nyc.gov/about-us/vision-and-mission/artificial-intelligence/guidance-on-artificial-intelligence-full | J14: Cautious | K14: Required | L14: Hybrid | M14: AI Literacy | N14: Pedagogy/Learning | O14: Referenced to integrity code | P14: Whole community | Q14: “The NYCPS Traffic Light Approach… establishes when AI use is prohibited, when AI use requires careful consideration and judgment, and when AI is approved for use.” | S14: EY | V14: {=XLOOKUP($I14,TEST_NYC_Coding!$I$5:$I$44,TEST_NYC_Coding!$A$5:$A$44,"")}
A15: NYC-011 | B15: Institutional | C15: NYC | D15: New York University | E15: NYU | F15: NYU Information Technology AI Primer | G15: FAQ/Resource Page | I15: https://www.nyu.edu/life/information-technology/artificial-intelligence-at-nyu/primer.html | J15: Functional | K15: Not specified | L15: Not specified | M15: AI Literacy | N15: Privacy/Data/Ethics | O15: Guidance only | P15: Whole community | Q15: While the models are immensely powerful tools, they require careful integration, governance, and human oversight to manage issues like bias, misinformation (hallucinations), and intellectual property, ensuring their power is used responsibly. | S15: EY | V15: {=XLOOKUP($I15,TEST_NYC_Coding!$I$5:$I$44,TEST_NYC_Coding!$A$5:$A$44,"")}
A16: NYC-012 | B16: Institutional | C16: NYC | D16: New York University | E16: NYU | F16: Student Learning with Generative AI | G16: FAQ/Resource Page | I16: https://www.nyu.edu/faculty/teaching-and-learning-resources/Student-Learning-with-Generative-AI.html | J16: Functional | K16: Recommended | L16: Institution-mandated | M16: AI Literacy | N16: Pedagogy/Learning | O16: Guidance only | P16: Students and Faculty | Q16: Students and faculty may use AI tools for learning and research; they should understand how AI works, evaluate outputs critically, and cite AI use where appropriate | S16: EY | V16: {=XLOOKUP($I16,TEST_NYC_Coding!$I$5:$I$44,TEST_NYC_Coding!$A$5:$A$44,"")}
A17: NYC-013 | B17: Institutional | C17: NYC | D17: New York University | E17: NYU | F17: Adapting Assignments to Generative AI | G17: University Policy | I17: https://www.nyu.edu/faculty/teaching-and-learning-resources/teaching-with-generative-tools/adapting-assignments-to-generative-AI.html | J17: Functional | K17: Recommended | L17: Instructor decides | M17: AI Literacy | N17: Academic Integrity | O17: Referenced to integrity code | P17: Faculty only | Q17: Even if an instructor does not intend to change individual assignments, the availability and generality of these tools increases the need for clarity around the instructor’s expectations. Whatever strategies an instructor might adopt for individual assignments or a whole course, instructors should explain to students what is expected around AI use. | S17: EY | V17: {=XLOOKUP($I17,TEST_NYC_Coding!$I$5:$I$44,TEST_NYC_Coding!$A$5:$A$44,"")}
A18: NYC-014 | B18: Institutional | C18: NYC | D18: New York University | E18: NYU | F18: Frequently Asked Questions About Teaching and AI | G18: FAQ/Resource Page | H18: 45708 | I18: https://www.nyu.edu/faculty/teaching-and-learning-resources/teaching-with-generative-tools/frequently-asked-questions.html | J18: Functional | K18: Recommended | L18: Instructor decides | M18: Pedagogy/Learning | N18: Academic Integrity | O18: Guidance only | P18: Faculty only | Q18: "Generative AI is a new arrival in the academic environment and can be used in a wide variety of ways. Because of this novelty and flexibility, there are few standard approaches to its use beyond an Faculty/Inst. decides restriction on taking credit for AI output without acknowledging its use. Most policies will be set by the schools or by individual faculty members." | S18: EY | V18: {=XLOOKUP($I18,TEST_NYC_Coding!$I$5:$I$44,TEST_NYC_Coding!$A$5:$A$44,"")} -> NYC-012
A19: NYC-015 | B19: Institutional | C19: NYC | D19: New York University | E19: NYU | F19: NYU AI Center of Excellence | G19: FAQ/Resource Page | I19: https://www.nyu.edu/life/information-technology/artificial-intelligence-at-nyu/coe.html | J19: Encouraging | K19: Not specified | L19: Institution-mandated | M19: AI Literacy | N19: Pedagogy/Learning | O19: Guidance only | P19: Whole community | Q19: “New York University is strategically investing in AI to gain significant administrative efficiencies, accelerate cutting-edge research, and equip our entire community—faculty, students, and staff—with the tools to thrive in an AI-driven world.” | S19: EY | V19: {=XLOOKUP($I19,TEST_NYC_Coding!$I$5:$I$44,TEST_NYC_Coding!$A$5:$A$44,"")}
A20: NYC-016 | B20: Institutional | C20: NYC | D20: City University of New York | E20: CUNY | F20: CUNY AI Academic Hub | G20: University Policy | H20: 2025 | I20: https://www.cuny.edu/academics/ai-academic-hub/ | J20: Encouraging | K20: Not specified | L20: Not specified | M20: AI Literacy | N20: Professional Readiness | O20: Guidance only | P20: Students and Faculty | Q20: "Our Vision is shaping the Future of Human-AI Powered Education. CUNY is at the forefront of AI-driven transformation in higher education. Our mission is to harness AI’s potential to empower learning, drive research, and foster innovation—ensuring equitable opportunities for all." | S20: EY | V20: {=XLOOKUP($I20,TEST_NYC_Coding!$I$5:$I$44,TEST_NYC_Coding!$A$5:$A$44,"")} -> NYC-017
A21: NYC-017 | B21: Institutional | C21: NYC | D21: City University of New York | E21: CUNY | F21: Teach@CUNY AI Toolkit | G21: FAQ/Resource Page | I21: https://aitoolkit.commons.gc.cuny.edu/ | J21: Cautious | K21: Recommended | L21: Instructor decides | M21: AI Literacy | N21: Pedagogy/Learning | O21: Guidance only | P21: Students and Faculty | Q21: “This toolkit offers guidelines and resources to help instructors support students as we all learn to navigate a world increasingly awash in AI.” | S21: EY | V21: {=XLOOKUP($I21,TEST_NYC_Coding!$I$5:$I$44,TEST_NYC_Coding!$A$5:$A$44,"")}
A22: NYC-018 | B22: Institutional | C22: NYC | D22: City University of New York | E22: CUNY | F22: CUNY Central Academic Integrity Policy | G22: University Policy | H22: 2024 | I22: https://www.cuny.edu/about/administration/offices/legal-affairs/policies-resources/academic-integrity-policy/ | J22: Cautious | K22: Required | L22: Hybrid | M22: Academic Integrity | N22: AI Literacy | O22: Explicit penalties | P22: Students and Faculty | Q22: “Any use of generative AI tools must be in line with the usage policy for specific assignments as defined in the course of the syllabus and/or communicated by the course instructor.” | S22: EY | V22: {=XLOOKUP($I22,TEST_NYC_Coding!$I$5:$I$44,TEST_NYC_Coding!$A$5:$A$44,"")}
A23: NYC-019 | B23: Institutional | C23: NYC | D23: City University of New York | E23: CUNY | F23: AI Across CUNY | G23: FAQ/Resource Page | H23: 45930 | I23: https://www.ccny.cuny.edu/tlc/making-your-course-available?srsltid=AfmBOoojIHHL2OxDCdrK-0Xc9elMyrAnNWVcOtEzwybtMdTvH4Pbcfy- | J23: Encouraging | K23: Required | L23: Instructor decides | M23: AI Literacy | N23: Pedagogy/Learning | O23: None stated | P23: Students and Faculty | Q23: “The Teaching and Learning Center developed this resource to help faculty explore the intersection of AI and education.” | S23: EY | V23: {=XLOOKUP($I23,TEST_NYC_Coding!$I$5:$I$44,TEST_NYC_Coding!$A$5:$A$44,"")} -> NYC-020
A24: NYC-020 | B24: Institutional | C24: NYC | D24: City University of New York | CUNY Central Office / CUNY Innovative Teaching Academy | E24: CUNY | F24: Teaching with AI: Disciplinary Toolkits | G24: FAQ/Resource Page | H24: 2024-2025 | I24: https://www.cuny.edu/academics/faculty-affairs/faculty-hub/cuny-innovative-teaching-academy/building-bridges-of-knowledge-bbk/#1743443301057-e01b194c-474d | J24: Encouraging | K24: Not specified | L24: Instructor decides | M24: AI Literacy | N24: Professional Readiness | O24: None stated | P24: Students and Faculty | Q24: “Building Bridge of Knowledge (BBK) is a CUNY-wide faculty fellowship project, aiming to help students use generative artificial intelligence (AI) tools ethically, responsibly, and effectively.” | S24: EY | V24: {=XLOOKUP($I24,TEST_NYC_Coding!$I$5:$I$44,TEST_NYC_Coding!$A$5:$A$44,"")}
A25: NYC-021 | B25: Institutional | C25: NYC | D25: Columbia University / Office of the Provost | E25: Columbia | F25: Office of the Provost: Generative AI Policy & Guidance (2024-2026) | G25: University Policy | I25: https://provost.columbia.edu/content/generative-ai | J25: Cautious | K25: Required | L25: Hybrid | M25: Privacy/Data/Ethics | N25: Academic Integrity | O25: Referenced to integrity code | P25: Whole community | Q25: “Columbia recognizes that generative AI is a tool that is transforming higher education and society, and encourages our campus community to explore its possibilities while being mindful of the potential security and privacy risks that it poses.” | S25: EY | V25: {=XLOOKUP($I25,TEST_NYC_Coding!$I$5:$I$44,TEST_NYC_Coding!$A$5:$A$44,"")}
A26: NYC-022 | B26: Institutional | C26: NYC | D26: Columbia University Information Technology / Emerging Technologies | E26: Columbia | F26: Best Practices for Responsible AI Use | G26: University Policy | H26: 46031 | I26: https://etc.cuit.columbia.edu/news/best-practices-responsible-ai-use | J26: Cautious | K26: Required | L26: Hybrid | M26: Privacy/Data/Ethics | N26: AI Literacy | O26: Referenced to integrity code | P26: Whole community | Q26: CUIT’s guidance is designed to help the Columbia community benefit from AI while avoiding common failure points, particularly when institutional or sensitive data is involved. At the center of the guidance is one principle: AI should assist human judgment, not replace i | S26: EY | V26: {=XLOOKUP($I26,TEST_NYC_Coding!$I$5:$I$44,TEST_NYC_Coding!$A$5:$A$44,"")} -> NYC-011
A27: NYC-023 | B27: Institutional | C27: NYC | D27: Columbia University | E27: Columbia | F27: Columbia CTL AI Guidelines (2024-2026) | G27: University Policy | I27: https://ctl.columbia.edu/resources-and-technology/resources/academic-integrity/ | J27: Cautious | K27: Required | L27: Instructor decides | M27: Academic Integrity | N27: AI Literacy | O27: Referenced to integrity code | P27: Students and Faculty | Q27: “The possible advantages that might present in the teaching-learning process should be under the control of each instructor since they know exactly what they expect from students’ work.” | S27: EY | V27: {=XLOOKUP($I27,TEST_NYC_Coding!$I$5:$I$44,TEST_NYC_Coding!$A$5:$A$44,"")}
A28: NYC-024 | B28: Institutional | C28: NYC | D28: Columbia University | E28: Columbia | F28: CUIT AI Framework Policy | G28: FAQ/Resource Page | H28: 45818 | I28: https://www.cuit.columbia.edu/sites/www.cuit.columbia.edu/files/content/CUIT%20Website%20Pages/AI%20Framework%20%20(1).pdf | J28: Encouraging | K28: Recommended | L28: Institution-mandated | M28: Privacy/Data/Ethics | O28: Guidance only | P28: Whole community | Q28: “A key tenet of the framework is governance — ensuring that all AI initiatives adhere to security, privacy, and compliance requirements from the outset.” | S28: EY | V28: {=XLOOKUP($I28,TEST_NYC_Coding!$I$5:$I$44,TEST_NYC_Coding!$A$5:$A$44,"")}
A29: NYC-025 | B29: Institutional | C29: NYC | D29: Columbia University | E29: Columbia | F29: CUIT Generative AI Data Security Guidelines | G29: University Policy | I29: https://www.cuit.columbia.edu/content/ai-services | J29: Encouraging | K29: Not specified | L29: Institution-mandated | M29: AI Literacy | O29: Guidance only | P29: Whole community | Q29: “For work involving non-public data, Columbia IT maintains a set of enterprise-grade AI tools — including Columbia ChatGPT Education, CHAT, and Google for Education — that operate within a secured environment sometimes called a ‘walled garden.’” | S29: EY | V29: {=XLOOKUP($I29,TEST_NYC_Coding!$I$5:$I$44,TEST_NYC_Coding!$A$5:$A$44,"")}
A30: NYC-026 | B30: Faculty/Department | C30: NYC | D30: New York University - Steinhardt | E30: NYU | F30: NYU Steinhardt - Academic Integrity and Syllabus Support in the Age of Generative AI | G30: FAQ/Resource Page | I30: https://steinhardt.nyu.edu/faculty-and-staff/academic-affairs/steinhardt-ai-hub/academic-integrity-and-syllabus-support-age | J30: Cautious | K30: Required | L30: Faculty/Dept decides | M30: AI Literacy | N30: Pedagogy/Learning | O30: Referenced to integrity code | P30: Faculty only | Q30: “Any AI-generated content used in assignments must be properly attributed.” | S30: EY | T30: 46157 | V30: {=XLOOKUP($I30,TEST_NYC_Coding!$I$5:$I$44,TEST_NYC_Coding!$A$5:$A$44,"")} -> NYC-013
A31: NYC-027 | B31: Faculty/Department | C31: NYC | D31: New York University - CAS | E31: NYU | F31: CAS - Expository Writing Program (EWP) Statement on AI (2026) | G31: University Policy | H31: 45962 | I31: https://cas.nyu.edu/ewp/about/statement-on-generative-ai.html | J31: Prohibitive | K31: Conditional | L31: Hybrid | M31: Pedagogy/Learning | N31: Academic Integrity | O31: Guidance only | P31: Students and Faculty | Q31: No EWP class permits students to use AI-generated writing unless it is clearly identified as an object for analysis | S31: EY | T31: 46157 | V31: {=XLOOKUP($I31,TEST_NYC_Coding!$I$5:$I$44,TEST_NYC_Coding!$A$5:$A$44,"")}
A32: NYC-028 | B32: Faculty/Department | C32: NYC | D32: New York University | E32: NYU | F32: Academic Integrity - Tisch | G32: University Policy | I32: https://tisch.nyu.edu/faculty/academic-integ | J32: Cautious | K32: Not specified | L32: Instructor decides | M32: Academic Integrity | N32: Pedagogy/Learning | O32: Explicit penalties | P32: Students and Faculty | Q32: Generative AI: Please note, with recent developments in technologies like ChatGPT, the existence of a well-written paragraph is no longer evidence of human effort. To read the Provost's notes on how to adapt writing assignments in the age of generative AI, click here. | S32: EY | T32: 46157 | V32: {=XLOOKUP($I32,TEST_NYC_Coding!$I$5:$I$44,TEST_NYC_Coding!$A$5:$A$44,"")} -> NYC-015
A33: NYC-029 | B33: Faculty/Department | C33: NYC | D33: New York University | E33: NYU | F33: Generative AI Updates – Live Syllabus and Faculty Development Resources | G33: FAQ/Resource Page | H33: 45314 | I33: https://wp.nyu.edu/fas-edtech/2024/01/generative-ai-updates-live-syllabus-and-faculty-development-resources/ | J33: Cautious | K33: Recommended | L33: Instructor decides | M33: Pedagogy/Learning | N33: Academic Integrity | O33: Guidance only | P33: Faculty only | Q33: “Whatever your approach, clear communication with students about your expectations and your justification for your generative AI use policies should be on your beginning of the semester agenda.” | S33: EY | T33: 46157 | V33: {=XLOOKUP($I33,TEST_NYC_Coding!$I$5:$I$44,TEST_NYC_Coding!$A$5:$A$44,"")}
A34: NYC-030 | B34: Faculty/Department | C34: NYC | D34: New York University | E34: NYU | F34: Generative AI Resources for Faculty - NYU Arts and Sciences | G34: FAQ/Resource Page | I34: https://as.nyu.edu/academics/teaching-excellence-and-innovation/services/course-support/genai-resources.html | J34: Cautious | K34: Not specified | L34: Instructor decides | M34: AI Literacy | N34: Academic Integrity | O34: Guidance only | P34: Faculty only | Q34: “The materials on this page are a regularly updated collection of the advice and resources our team shares with instructors and departments about AI and teaching and learning.” | S34: EY | T34: 46157 | V34: {=XLOOKUP($I34,TEST_NYC_Coding!$I$5:$I$44,TEST_NYC_Coding!$A$5:$A$44,"")}
A35: NYC-031 | B35: Faculty/Department | C35: NYC | D35: CUNY - Baruch College | E35: CUNY | F35: Guidelines for AI Use at Baruch College | G35: Official Guidance | H35: 45888 | I35: https://provost.baruch.cuny.edu/artificial-intelligence-think-tank/ai-use-guidance/ | J35: Encouraging | K35: Required | L35: Instructor decides | M35: Pedagogy/Learning | N35: Privacy/Data/Ethics | O35: Referenced to integrity code | P35: Students and Faculty | Q35: "Faculty are encouraged to integrate artificial intelligence education into their courses as appropriate to their disciplines, but are not obligated to do so. All syllabi should include a course- and discipline-appropriate policy on the use of generative AI." | S35: EY | T35: 46157 | V35: {=XLOOKUP($I35,TEST_NYC_Coding!$I$5:$I$44,TEST_NYC_Coding!$A$5:$A$44,"")} -> NYC-018
A36: NYC-032 | B36: Faculty/Department | C36: NYC | D36: CUNY - John Jay College of Criminal Justice | E36: CUNY | F36: AI Responsible Use Guidelines | G36: Official Guidance | I36: https://www.jjay.cuny.edu/about/senior-leadership/academic-affairs/office-provost/ai-policies-guidelines | J36: Functional | K36: Required | L36: Institution-mandated | M36: Academic Integrity | N36: AI Literacy | O36: Referenced to integrity code | P36: Whole community | Q36: Generative AI is a powerful tool for research and scholarship, and its effective use is becoming an essential workplace skill. We believe that fostering AI literacy across all disciplines is an extension of our mission to prepare students for meaningful careers and ethical leadership within the justice system and beyond. | R36: There are 3 documents, For Everyone, For Student and For Faculty. All of them were considered in this coding | S36: EY | T36: 46157 | V36: {=XLOOKUP($I36,TEST_NYC_Coding!$I$5:$I$44,TEST_NYC_Coding!$A$5:$A$44,"")}
A37: NYC-033 | B37: Faculty/Department | C37: NYC | D37: CUNY - LaGuardia | E37: CUNY | F37: Teaching Writing at LaGuardia Generative AI Guidance. | G37: Official Guidance | I37: https://lagccwriting.commons.gc.cuny.edu/gen-ai-guidance/ | J37: Functional | K37: Recommended | L37: Instructor decides | M37: Pedagogy/Learning | N37: Academic Integrity | O37: Referenced to integrity code | P37: Students and Faculty | Q37: Please include a statement on your syllabus which indicates your policy about student use of AI in your class. Please also verbally reinforce this policy with students throughout the semester. Right now, the Department does not have a uniform policy. To help you decide on your policy, here are some guiding resources: | S37: EY | T37: 46157 | V37: {=XLOOKUP($I37,TEST_NYC_Coding!$I$5:$I$44,TEST_NYC_Coding!$A$5:$A$44,"")}
A38: NYC-034 | B38: Faculty/Department | C38: NYC | D38: CUNY - City Tech | E38: CUNY | F38: City Tech Artificial Intelligence Guidance | G38: Official Guidance | I38: https://www.citytech.cuny.edu/ai/ai-guidance.aspx | J38: Cautious | K38: Required | L38: Hybrid | M38: Privacy/Data/Ethics | N38: Academic Integrity | O38: Referenced to integrity code | P38: Whole community | Q38: City Tech recognizes the rapid evolution of Artificial Intelligence (AI) and its impact on how we work, teach and learn. As the landscape of AI changes, and Generative AI tools become widely available for everyday use, new opportunities in higher education are realized, but also present new risks that must be taken into consideration when using these technologies. We encourage you to experiment with AI tools, but also consider the following guidelines which align with existing CUNY and City Tech policies on information security and academic integrity. Please consider the guidelines in conjunction with other CUNY recommendations and policies. | R38: There are 3 documents, For Everyone, For Student and For Faculty. All of them were considered in this coding | S38: EY | T38: 46157 | V38: {=XLOOKUP($I38,TEST_NYC_Coding!$I$5:$I$44,TEST_NYC_Coding!$A$5:$A$44,"")}
A39: NYC-035 | B39: Faculty/Department | C39: NYC | D39: CUNY - Queens College | E39: CUNY | F39: Generative AI in the Classroom: Best Practices, a CETLL Guide | G39: FAQ/Resource Page | H39: 45717 | I39: https://www.qc.cuny.edu/cetll/wp-content/uploads/sites/138/2026/03/Generative-AI-in-the-Classroom-Best-Practices-a-CETLL-Guide_ACCESSIBLE_3.19.pdf | J39: Functional | K39: Recommended | L39: Instructor decides | M39: Pedagogy/Learning | N39: AI Literacy | O39: Guidance only | P39: Faculty only | Q39: Currently, there is no specific CUNY or QC policy on the use of artificial intelligence in the classroom outside of mentions of AI in the CUNY Academic Integrity Policy. This means that, as instructors, we have a lot of flexibility and responsibility to consider how and when the use of generative AI is acceptable in our classes to clearly communicate these parameters to our students as we prepare them for the integration of these technologies in work and life. | S39: EY | T39: 46157 | V39: {=XLOOKUP($I39,TEST_NYC_Coding!$I$5:$I$44,TEST_NYC_Coding!$A$5:$A$44,"")} -> NYC-022
A40: NYC-036 | B40: Faculty/Department | C40: NYC | D40: Teachers College, Columbia University | E40: Columbia | F40: TC Guidance - Developing a Generative AI Policy for Your Course | G40: FAQ/Resource Page | H40: 2025 | I40: https://www.tc.columbia.edu/digitalfuturesinstitute/ai-in-education/recommendations-for-generative-ai-use-at-tc/ | J40: Functional | K40: Conditional | L40: Instructor decides | M40: Pedagogy/Learning | N40: Academic Integrity | O40: Referenced to integrity code | P40: Students and Faculty | Q40: "TC provides flexibility for instructors to experiment with and use generative AI in their courses. Each TC instructor should set specific policies about student use of generative AI for their course assignments" | S40: EY | T40: 46156 | V40: {=XLOOKUP($I40,TEST_NYC_Coding!$I$5:$I$44,TEST_NYC_Coding!$A$5:$A$44,"")} -> NYC-023
A41: NYC-037 | B41: Faculty/Department | C41: NYC | D41: Columbia Law School | E41: Columbia | F41: Columbia Law School Interim Policy on Generative AI | G41: University Policy | I41: https://www.law.columbia.edu/academics/registration-services/resources/columbia-law-school-interim-policy-generative-ai | J41: Cautious | K41: Not specified | L41: Hybrid | M41: Academic Integrity | N41: AI Literacy | O41: Referenced to integrity code | P41: Students and Faculty | Q41: Generative AI includes any machine-based tool designed to help write, rewrite, or restructure language from user questions and prompts. Prohibited tools include, for example, Bard, ChatGPT, Gemini, Grok, along with embedded tools in programs such as Grammarly or Microsoft Copilot. Generative AI is distinct from software that helps search for and extract information from data sources for use in research. (...) Use of Generative AI is prohibited in (a) any exam or final paper or (b) for aid in drafting any part of work submitted for credit, even if the use is fully documented. The Law School and University Generative AI policies are default rules. This means individual instructors can, and indeed are encouraged to, tailor their own more permissive policies, so long as their policies are stated in writing in the syllabus. | S41: EY | T41: 46156 | V41: {=XLOOKUP($I41,TEST_NYC_Coding!$I$5:$I$44,TEST_NYC_Coding!$A$5:$A$44,"")}
A42: NYC-038 | B42: Faculty/Department | C42: NYC | D42: Columbia Business School | E42: Columbia | F42: Columbia Business School - Getting Started with Generative Artificial Intelligence | G42: University Policy | I42: https://business.columbia.edu/samberg/ai/ai-basics | J42: Encouraging | K42: Required | L42: Institution-mandated | M42: AI Literacy | N42: Privacy/Data/Ethics | O42: None stated | P42: Whole community | Q42: “Generative AI is a powerful tool capable of creating innovative solutions, automating repetitive tasks, and enhancing productivity.” | S42: EY | T42: 46156 | V42: {=XLOOKUP($I42,TEST_NYC_Coding!$I$5:$I$44,TEST_NYC_Coding!$A$5:$A$44,"")}
A43: NYC-039 | B43: Faculty/Department | C43: NYC | D43: Center for Teaching and Learning (CTL) | E43: Columbia | F43: Center for Teaching and Learning (CTL) - Developing AI Syllabus Statements and Communicating with Students about AI | G43: University Policy | I43: https://ai.ctl.columbia.edu/explore/ai-syllabus-statement/ | J43: Functional | K43: Required | L43: Hybrid | M43: Pedagogy/Learning | N43: Academic Integrity | O43: Referenced to integrity code | P43: Students and Faculty | Q43: “Since instructors and academic departments have the ability to develop their own AI course policies, students may encounter different guidelines across their courses.” | S43: EY | T43: 46156 | V43: {=XLOOKUP($I43,TEST_NYC_Coding!$I$5:$I$44,TEST_NYC_Coding!$A$5:$A$44,"")}
A44: NYC-040 | B44: Faculty/Department | C44: NYC | D44: Columbia University Irving Medical Center | E44: Columbia | F44: AI and Generative Technology Use at CUIMC | G44: University Policy | I44: https://www.it.cuimc.columbia.edu/ai-and-generative-technology-use-cuimc | J44: Cautious | K44: Required | L44: Institution-mandated | M44: Privacy/Data/Ethics | N44: AI Literacy | O44: Guidance only | P44: Whole community | Q44: “All use of AI, Large Language Models (LLM), Natural Language processors (NLP) or Machine Learning (ML) systems at the Medical Center must comply with HIPAA and other relevant healthcare and IT regulations.” | S44: EY | T44: 46156 | V44: {=XLOOKUP($I44,TEST_NYC_Coding!$I$5:$I$44,TEST_NYC_Coding!$A$5:$A$44,"")}
A45: NYC-041 | B45: Course-wide | C45: NYC | D45: NYU Stern | E45: NYU | F45: Global Strategy (Stern School of Business) Global Strategy Syllabus | G45: Syllabus | H45: Fall 2025 | I45: https://web-apps-shib.stern.nyu.edu/syllabi/static/syllabusfiles/MGMT-GB.2340_10_F2025.pdf | J45: Prohibitive | K45: Required | L45: Instructor decides | M45: Academic Integrity | N45: Pedagogy/Learning | O45: Explicit penalties | P45: Students only | Q45: In this course, students are not allowed to use advanced automated tools (artificial intelligence or machine learning tools) on any component of this course. (...) When you are doing research for your final project, please make sure you use credible resources that are not generated by AI. If any part of your assignment(s) are produced by AI, I will ask you to redo that section or the assignment. I will not grade or provide feedback on an AI generated text. | S45: EY | T45: 46156 | V45: {=XLOOKUP($I45,TEST_NYC_Coding!$I$5:$I$44,TEST_NYC_Coding!$A$5:$A$44,"")}
A46: NYC-042 | B46: Course-wide | C46: NYC | D46: NYU Stern | E46: NYU | F46: Leadership (Stern School of Business - FT MBA) Leadership MBA Syllabus | G46: Syllabus | H46: Fall 2025 | I46: https://web-apps-shib.stern.nyu.edu/syllabi/static/syllabusfiles/COR1-GB.1102_02_F2025.pdf | J46: Prohibitive | K46: Not specified | L46: Instructor decides | M46: Academic Integrity | N46: Pedagogy/Learning | O46: Referenced to integrity code | P46: Students only | Q46: You can only learn from work you actually do. Unless otherwise stated, you should not use generative AI tools to create any part of an assignment in this course; every submission should be entirely your work. | S46: EY | T46: 46156 | V46: {=XLOOKUP($I46,TEST_NYC_Coding!$I$5:$I$44,TEST_NYC_Coding!$A$5:$A$44,"")}
A47: NYC-043 | B47: Course-wide | C47: NYC | D47: NYU College of Arts & Sciences | E47: NYU | F47: Texts and Ideas: CORE-UA 400 070 (College of Arts & Science) Texts and Ideas Syllabus | G47: Syllabus | H47: 2025 | I47: https://cas.nyu.edu/content/dam/nyu-as/casCore/documents/syllabifall2025/BARBIERO%20SYLLABUS%202025%20-%20Copy%20%281%29.pdf | J47: Prohibitive | K47: Not specified | L47: Instructor decides | M47: Pedagogy/Learning | N47: Academic Integrity | O47: Referenced to integrity code | P47: Students only | Q47: As with any other class work generated by anyone other than the students, whether by other students or by a company, use of AI in this class, unless specifically permitted, will be considered a violation of NYU’s Academic Integrity policy and will be dealt with accordingly. | S47: EY | T47: 46156 | V47: {=XLOOKUP($I47,TEST_NYC_Coding!$I$5:$I$44,TEST_NYC_Coding!$A$5:$A$44,"")}
A48: NYC-044 | B48: Course-wide | C48: NYC | D48: NYU College of Arts & Sciences | E48: NYU | F48: Environmental Justice & Inequality | G48: Syllabus | H48: Spring 2025 | I48: https://as.nyu.edu/content/dam/nyu-as/environment/documents/Syllabi/spring-2025/Environmental%20Justice%20syllabus%202025%20-%20Colin%20Jerolmack.pdf | J48: Prohibitive | K48: Required | L48: Institution-mandated | M48: Academic Integrity | N48: Pedagogy/Learning | O48: Explicit penalties | P48: Students only | Q48: “Presenting writing or data generated by someone else, or by software/Artificial Intelligence, as one’s own is a serious offense.” | S48: EY | T48: 46156 | V48: {=XLOOKUP($I48,TEST_NYC_Coding!$I$5:$I$44,TEST_NYC_Coding!$A$5:$A$44,"")}
A49: NYC-045 | B49: Course-wide | C49: NYC | D49: NYU College of Arts & Sciences | E49: NYU | F49: Writing Program Course Syllabus (College of Arts & Science) FAS Writing Syllabus: “Language as a Site of Protest: Poetry & Prose of the Political Imagination” | G49: Syllabus | H49: Fall 2025 | I49: https://as.nyu.edu/content/dam/nyu-as/cwp/documents/introsyllabi/fall2025syllabi/NYU%20Syllabus,%20Fall%202025%20-%20GDC-9.pdf | J49: Prohibitive | K49: Not specified | L49: Instructor decides | M49: Academic Integrity | N49: Pedagogy/Learning | O49: Explicit penalties | P49: Students only | Q49: “Plagiarism will be reported to the department, without exception. This includes the use of AI.” | S49: EY | T49: 46156 | V49: {=XLOOKUP($I49,TEST_NYC_Coding!$I$5:$I$44,TEST_NYC_Coding!$A$5:$A$44,"")}
A50: NYC-046 | B50: Course-wide | C50: NYC | D50: CUNY - Lemann College | E50: CUNY | F50: English 111: Composition I Course Syllabus | G50: Syllabus | H50: 2025 | I50: https://academicworks.cuny.edu/cgi/viewcontent.cgi?article=1112&context=le_oers | J50: Prohibitive | K50: Not specified | L50: Instructor decides | M50: Academic Integrity | N50: Pedagogy/Learning | O50: Referenced to integrity code | P50: Students only | Q50: While AI and Chat GPT is the future, it is not a valid resource for this class. As we will discuss, any time you are creating an assignment it must be in your own words. The use of AI, ChatGPT, etc. presenting as your own work that you yourself have not written will be considered plagiarism | S50: EY | T50: 46156 | V50: {=XLOOKUP($I50,TEST_NYC_Coding!$I$5:$I$44,TEST_NYC_Coding!$A$5:$A$44,"")}
A51: NYC-047 | B51: Course-wide | C51: NYC | D51: CUNY - City College | E51: CUNY | F51: MCA 10100: Introduction to Mass Media OER/ZTC Syllabus | G51: Syllabus | H51: 2025 | I51: https://academicworks.cuny.edu/cgi/viewcontent.cgi?article=1583&context=cc_oers | J51: Functional | K51: Not specified | L51: Instructor decides | M51: Academic Integrity | N51: Pedagogy/Learning | O51: Referenced to integrity code | P51: Students only | Q51: As such, while using some programs of sites with AI features to do simple things like correct grammar or edit work is permissible, using generative AI programs like ChatGPT to write assignments for yourself will be considered an act of turning in work that is not your own and violate academic honesty guidelines. | S51: EY | T51: 46156 | V51: {=XLOOKUP($I51,TEST_NYC_Coding!$I$5:$I$44,TEST_NYC_Coding!$A$5:$A$44,"")}
A52: NYC-048 | B52: Course-wide | C52: NYC | D52: CUNY - York College | E52: CUNY | F52: Digital Cultures, DEI, and AI: Critical Analysis Assignment & Curriculum | G52: Syllabus | H52: 2026 | I52: https://academicworks.cuny.edu/cgi/viewcontent.cgi?article=1094&context=jj_oers | J52: Functional | K52: Required | L52: Instructor decides | M52: AI Literacy | N52: Academic Integrity | O52: Guidance only | P52: Students only | Q52: Students may use AI tools only for: brainstorming, outlining, or organizing ideas. AI tools may not replace original thinking or writing. If AI is used, students must include a brief AI Use Disclosure Statement explaining: which tool was used, how it was used, and how authorship decisions remained human-directed | S52: EY | T52: 46156 | V52: {=XLOOKUP($I52,TEST_NYC_Coding!$I$5:$I$44,TEST_NYC_Coding!$A$5:$A$44,"")}
A53: NYC-049 | B53: Course-wide | C53: NYC | D53: CUNY - Queens College | E53: CUNY | F53: Queens College — FNES 722 (Exercise, Energy Balance, and Body Composition) | G53: Syllabus | H53: 2025 | I53: https://academicworks.cuny.edu/cgi/viewcontent.cgi?article=1117&context=qc_oers | J53: Cautious | K53: Required | L53: Instructor decides | M53: Academic Integrity | N53: AI Literacy | O53: Explicit penalties | P53: Students only | Q53: Cheating is the unauthorized use or attempted use of material, information, notes, study aids, devices, artificial intelligence (AI) systems, or communication during an academic exercise and will result in a grade of a “0” on the assignment and may result in disciplinary action from the department/University. | S53: EY | T53: 46156 | V53: {=XLOOKUP($I53,TEST_NYC_Coding!$I$5:$I$44,TEST_NYC_Coding!$A$5:$A$44,"")}
A54: NYC-050 | B54: Course-wide | C54: NYC | D54: CUNY - Baruch College | E54: CUNY | F54: Baruch College — ENV 3070 (Agroecology) | G54: Syllabus | H54: 2025 | I54: https://academicworks.cuny.edu/cgi/viewcontent.cgi?article=1129&context=bb_oers | J54: Encouraging | K54: Required | L54: Instructor decides | M54: Academic Integrity | O54: Referenced to integrity code | P54: Students only | Q54: Use of generative AI tools (e.g. ChatGPT) is allowed. For each written assignment where generative AI is employed, you must include a cover letter describing what tool(s) you used, how you used it, why it was useful, and any shortcomings or limitations you encountered | S54: EY | T54: 46156 | V54: {=XLOOKUP($I54,TEST_NYC_Coding!$I$5:$I$44,TEST_NYC_Coding!$A$5:$A$44,"")}
A55: NYC-051 | B55: Course-wide | C55: NYC | D55: Columbia University | E55: Columbia | F55: PSYC UN 3620: Developmental Psychopathology | G55: Syllabus | H55: Fall 2024 | I55: https://psychology.columbia.edu/sites/psychology.columbia.edu/files/content/PSYC%203620%20Syllabus%20Fall2024.pdf | J55: Functional | K55: Required | L55: Instructor decides | M55: Academic Integrity | N55: Pedagogy/Learning | O55: Referenced to integrity code | P55: Students only | Q55: While you are welcome to use generative AI tools in this class when doing so aligns with the course objectives, please be advised of the following (...) Remember, AI is not likely to generate a response that would be seen as quality work, and should be modified, personalized, and always properly cited. | S55: EY | T55: 46156 | V55: {=XLOOKUP($I55,TEST_NYC_Coding!$I$5:$I$44,TEST_NYC_Coding!$A$5:$A$44,"")}
A56: NYC-052 | B56: Course-wide | C56: NYC | D56: Columbia University | E56: Columbia | F56: COMS 3261: Computer Science Theory | G56: Syllabus | H56: Spring 2025 | I56: https://www.cs.columbia.edu/~josh/cs-theory/ | J56: Prohibitive | K56: Not specified | L56: Instructor decides | M56: Pedagogy/Learning | O56: None stated | P56: Students only | Q56: It is also prohibited to use generative AI tools like ChatGPT while working on homeworks. (Even if it were not prohibited, these tools typically give incorrect and confusing solutions to the types of problems we will see in this class. In fact, in this class, we will give a mathematical explanation for this phenomenon!) | S56: EY | T56: 46156 | V56: {=XLOOKUP($I56,TEST_NYC_Coding!$I$5:$I$44,TEST_NYC_Coding!$A$5:$A$44,"")}
A57: NYC-053 | B57: Course-wide | C57: NYC | D57: Columbia University | E57: Columbia | F57: NSBV BC3392: Psychobiology of Stress | G57: Syllabus | H57: Fall 2024 | I57: https://psychology.columbia.edu/sites/psychology.columbia.edu/files/content/Syllabus%20Psychobiology%20of%20Stress%20FA24.pdf | J57: Prohibitive | K57: Not specified | L57: Instructor decides | M57: Pedagogy/Learning | N57: Academic Integrity | O57: None stated | P57: Students only | Q57: Submitting work that is generated by AI is not acceptable. There are no shortcuts when it comes to learning how to write about and present your own research. Instead, you are expected to put in the time and effort required to create your own work, which will not only demonstrate your understanding of your research topic, but also your ability to think critically and creatively. Students are expected to take responsibility for their work to ensure that it is original and well-researched. | S57: EY | T57: 46156 | V57: {=XLOOKUP($I57,TEST_NYC_Coding!$I$5:$I$44,TEST_NYC_Coding!$A$5:$A$44,"")}
A58: NYC-054 | B58: Course-wide | C58: NYC | D58: Columbia University | E58: Columbia | F58: PSYC UN 2235: Thinking and Decision Making | G58: Syllabus | H58: Spring 2024 | I58: https://psychology.columbia.edu/sites/psychology.columbia.edu/files/content/UN2235%20Syllabus%20for%20Spring%202024%20KFG.pdf | J58: Functional | K58: Not specified | L58: Instructor decides | M58: Pedagogy/Learning | N58: Academic Integrity | O58: Referenced to integrity code | P58: Students only | Q58: Generative AI tools like ChatGPT and Bard can do a lot of heavy lifting in academic contexts. Such tools aren’t inherently good or bad—it’s all up to how you use them. Ultimately, the ideas and words you share in class and in your written work for this course should all be your own. In presentations, although you’re welcome to seek AI help in the aesthetics of your slides, the words presented in them should be your own. And in your policy paper and final papers, it’s fine to get AI help with editing, but the ideas on the page need to have been produced by you alone | S58: EY | T58: 46156 | V58: {=XLOOKUP($I58,TEST_NYC_Coding!$I$5:$I$44,TEST_NYC_Coding!$A$5:$A$44,"")}
A59: NYC-055 | B59: Course-wide | C59: NYC | D59: Columbia University | E59: Columbia | F59: COMS 4705: Natural Language Processing | G59: Syllabus | H59: Spring 2024 | I59: https://www.cs.columbia.edu/~johnhew/coms4705/index.html | J59: Functional | K59: Not specified | L59: Instructor decides | M59: Pedagogy/Learning | N59: Academic Integrity | O59: None stated | P59: Students only | Q59: AI tools (e.g., ChatGPT, Cursor, Claude Code) are fully allowed for Assignments 1–4. While I recommend doing the assignments on your own (or with minimal AI hints) as prep for exams, you may use AI to fully solve them if you wish. It is your responsibility to ensure that submitted code and math are correct. | S59: EY | T59: 46156 | V59: {=XLOOKUP($I59,TEST_NYC_Coding!$I$5:$I$44,TEST_NYC_Coding!$A$5:$A$44,"")}

Sheet TEST_HK_Coding
A1: Hong Kong Coding — GenAI Policy Coding
A2: Fill one row per policy document. Use dropdowns wherever possible. See tab '5_Codebook' for definitions.
A4: ID | B4: Tier | C4: Region | D4: Jurisdiction / Institution | E4: Institution | F4: Document Title | G4: Document Type | H4: Publication Date | I4: Source URL | J4: Stance | K4: Disclosure | L4: Discretion | M4: Focus (Primary) | N4: Focus (Secondary) | O4: Enforcement | P4: Coverage | Q4: Key Quote (verbatim) | R4: Coder Notes | S4: Coder | T4: Date Coded | U4: Coder Agreement (Initials if agree and DONT AGREE) | V4: No AI (teaching content is not AI policy)
A5: HK-001 | B5: National/Federal | C5: Hong Kong | D5: Central Government of the PRC (recorded by HKSAR Policy Address) | F5: Factsheets on “Outline of the 14th Five-Year Plan for National Economic and Social Development of the People’s Republic of China and the Long-Range Objectives Through the Year 2035” | G5: Official Guidance | H5: 2021 | I5: https://www.policyaddress.gov.hk/2021/eng/pdf/publications/14-5/14-5-full.pdf | J5: Encouraging | K5: Not specified | L5: Not specified | M5: Professional Readiness | O5: None stated | P5: All community | Q5: National Development Strategy: "..implement a batch of forward-looking and strategic national technological programmes focusing on frontier fields, including artificial intelligence,,," Central Government's Support for Hong Kong: "...support Hong Kong to develop into an international innovation and technology hub..." Promote the I&T development at full steam with new thinking, integrate into the overall development of the country and the Greater Bay Area (“GBA”) | R5: Due to "One Country, Two Systems", China laws/regulations do not directly affect Hong Kong. This national directive serves as the foundational mandate to develop Hong Kong into an international Innovation and Technology hub. | S5: YM | T5: 46138 | U5: cy
A6: HK-002 | B6: National/Federal | C6: Hong Kong | D6: The State Council of the People's Republic of China | F6: "AI Plus" guidelines (Chinese) | G6: Official Guidance | H6: 45896 | I6: https://www.mee.gov.cn/zcwj/gwywj/202508/t20250827_1126207.shtml | J6: Encouraging | K6: Not specified | L6: Gov-mandated | M6: Pedagogy/Learning | N6: AI Literacy | O6: None stated | P6: All community | Q6: 推行更富成效的学习方式。把人工智能融入教育教学全要素、全过程，创新智能学伴、智能教师等人机协同教育教学新模式，推动育人从知识传授为重向能力提升为本转变，加快实现大规模因材施教，提高教育质量，促进教育公平。构建智能化情景交互学习模式，推动开展方式更灵活、资源更丰富的自主学习。鼓励和支持全民积极学习人工智能新知识、新技术。 (Promote more effective learning methods. Integrate artificial intelligence into every element and stage of education and instruction; pioneer new human-machine collaborative models—such as intelligent learning companions and AI teachers—to drive a shift in pedagogy from a primary focus on knowledge transmission to one centered on capability enhancement; accelerate the realization of personalized instruction on a large scale; improve educational quality; and foster educational equity. Establish intelligent, context-aware interactive learning models to facilitate self-directed learning characterized by greater flexibility and richer resources. Encourage and support the entire populace in actively acquiring new knowledge and technologies related to artificial intelligence.) | R6: really postive with ai,from top tto down | S6: YM | T6: 46138 | U6: cy
A7: HK-003 | B7: State/Territory | C7: Hong Kong | D7: HKSAR Digital Policy Office | F7: Ethical Artificial Intelligence Framework | G7: Official Guidance | H7: 45991 | I7: https://www.digitalpolicy.gov.hk/en/our_work/data_governance/policies_standards/ethical_ai_framework/doc/Ethical_AI_Framework_en.pdf | J7: Cautious | K7: Recommended | L7: Gov-mandated | M7: Privacy/Data/Ethics | N7: AI Literacy | O7: Guidance only | P7: All community | Q7: The adoption of Ethical AI Framework is a step that establishes a common approach and structure to govern the development and deployment of AI applications with the intention to maximise the benefits of the application of AI in IT projects (...) | R7: detail in deep so can tell hksar really hyposis to manifest ai in different senaioro | S7: EY | T7: 46137 | U7: cy
A8: HK-004 | B8: State/Territory | C8: Hong Kong | D8: HKSAR Digital Policy Office | F8: Hong Kong Generative Artificial Intelligence Technical and Application Guideline | G8: Official Guidance | H8: 45992 | I8: https://www.digitalpolicy.gov.hk/en/our_work/data_governance/policies_standards/ethical_ai_framework/doc/HK_Generative_AI_Technical_and_Application_Guideline_en.pdf | J8: Cautious | K8: Required | L8: Gov-mandated | M8: Privacy/Data/Ethics | N8: AI Literacy | O8: Guidance only | P8: All community | Q8: "The Guideline aims to ensure the timely communication of governance developments and the sharing of best practices. It aims to balance innovation with social responsibility in the development of generative AI in Hong Kong, thereby maximising the benefits of technological advancement and minimising associated risks. " | S8: EY | T8: 46138 | U8: cy
A9: HK-005 | B9: State/Territory | C9: Hong Kong | D9: HKSAR Innovation, Technology and Industry Bureau | F9: Hong Kong Innovation and Technology Development Blueprint | G9: Official Guidance | H9: 44917 | I9: https://www.itib.gov.hk/en/publications/I&T%20Blueprint%20Book_EN_single_Digital.pdf | J9: Encouraging | K9: Not specified | L9: Gov-mandated | M9: Professional Readiness | N9: AI Literacy | O9: Guidance only | P9: All community | Q9: In the coming five years, the Government’s target is that 35% of the UGC-funded students will be studying subjects related to science, technology, engineering, arts and mathematics and 60% will be studying subjects relevant to Hong Kong’s development into the “eight centres/hubs” as stated in the 14th Five-Year Plan. The Government will also continue to encourage universities to offer more programmes related to science, technology, engineering, arts and mathematics. | U9: cy
A10: HK-006 | B10: State/Territory | C10: Hong Kong | D10: University Grants Committee (UGC) | F10: UGC establishes Fund for Innovative Technology-in-Education | G10: Official Guidance | H10: 45105 | I10: https://www.ugc.edu.hk/eng/ugc/about/press_speech_other/press/2023/pr20230628.html | J10: Encouraging | K10: Not specified | L10: Not specified | M10: Pedagogy/Learning | N10: AI Literacy | O10: Guidance only | P10: Researchers | Q10: The University Grants Committee (UGC), with support from its Quality Assurance Council (QAC), today (June 28) announced the launch of the Fund for Innovative Technology-in-Education (FITE) with a funding allocation of $100 million. "While it is widely acknowledged that digital competency plays a significant role in economic restructuring, there is also growing awareness of the ethical and social issues arising from the use of innovative technologies. In response to these changes, the UGC, with support from the QAC, launched the FITE to support experimental and exploratory endeavours of universities in enhancing their teaching and learning." | S10: EY | T10: 46138 | U10: cy
A11: HK-007 | B11: State/Territory | C11: Hong Kong | D11: news.gov.hk | F11: Cultivating AI innovation on campus | G11: Other | H11: 46138 | I11: https://www.news.gov.hk/eng/2026/04/20260424/20260424_152830_500.html | J11: Encouraging | K11: Not specified | L11: Not specified | M11: AI Literacy | N11: Pedagogy/Learning | O11: Guidance only | P11: Both | Q11: the 2026-27 Budget proposed $50 million to fuel a city-wide AI culture - supporting public bodies, technology companies and tertiary institutions in hosting courses and competitions as part of a roadmap to integrate AI education into everyday life. | S11: YM | T11: 46138 | U11: cy
A12: HK-008 | B12: State/Territory | C12: Hong Kong | D12: Legislative Council Panel on Education | F12: Major Policy Initiatives of the Education Bureau in 2026 | G12: Law/Regulation | I12: https://www.legco.gov.hk/yr2026/english/panels/ed/papers/ed20260127cb3-24-1-e.pdf | J12: Encouraging | K12: Not specified | L12: Not specified | M12: Pedagogy/Learning | N12: AI Literacy | O12: None stated | P12: All community | Q12: The EDB has earmarked $2 billion under the Quality Education Fund (QEF) to implement digital education development measures. Approximately $500 million of this amount will be allocated to the three-year 'AI for Empowering Learning and Teaching Funding Programme' | U12: cy
A13: HK-009 | B13: State/Territory | C13: Hong Kong | D13: AI Education UGC HKTEA AI CoP | F13: About Us | G13: FAQ/Resource Page | I13: https://aicop.hktea.hku.hk/about-us | J13: Encouraging | K13: Not specified | L13: Not specified | M13: Pedagogy/Learning | O13: None stated | P13: All community | Q13: supported by the Hong Kong University Grants Committee (UGC). It aims to bring together educators, administrators, and experts from Hong Kong’s higher education and school sectors, as well as those from HEIs around the world, to drive innovative implementation, share best practices, and strategize for the age of generative AI (GenAI). | R13: Not about rule enforcement | S13: YM | T13: 46138 | U13: cy
A14: HK-010 | B14: Institutional | C14: Hong Kong | D14: HKU Teaching and Learning Innovation Centre | E14: HKU | F14: HKU GenAI Services | G14: FAQ/Resource Page | I14: https://tl.hku.hk/genai/hku-genai-services/ | J14: Encouraging | K14: Not specified | L14: Not specified | M14: Pedagogy/Learning | N14: AI Literacy | O14: None stated | P14: Both | Q14: for staff and students to prepare for the future and reap benefits from the immense potential AI has to offer. Limited to teaching, learning, work and research-related purposes only, these AI assistants can help users resolve queries and assist in tasks. | S14: YM | T14: 46138 | U14: cy
A15: HK-011 | B15: Institutional | C15: Hong Kong | D15: HKU Libraries | E15: HKU | F15: AI Literacy - LibGuides at HKU | G15: Library Guide | I15: https://libguides.lib.hku.hk/AI-literacy/Home | J15: Encouraging | K15: Not specified | L15: Not specified | M15: AI Literacy | N15: Pedagogy/Learning | O15: Guidance only | P15: Both | Q15: This guide with curated learning resources aims to help HKU students and staff 1) deepen their understanding of AI, 2) learn about some Generative AI (GenAI) tools or AI-empowered tools that can enhance their learning and research experience, and 3) make individual decisions on selecting appropriate AI tools based on their own learning and research needs. | S15: YM | T15: 46138 | U15: cy
A16: HK-012 | B16: Institutional | C16: Hong Kong | D16: HKU (TaLiC) | E16: HKU | F16: Academic Integrity and University-wide Core Principles for Using AI | G16: Official Guidance | I16: https://talic.hku.hk/innovation/ai-ethics/core-principles/ | J16: Encouraging | K16: Conditional | L16: Instructor decides | M16: Academic Integrity | N16: Pedagogy/Learning | O16: Guidance only | P16: Both | Q16: Teachers must be very clear in their guidance to students as to what is acceptable use of AI within the activities of their course and specifically on their assignments intended for assessment. Part of the instructor’s guidance may be to require students to include details on how they have made use of AI when completing a task, but augment that with open dialogue and solicit feedback to help discover the nuances in regulating this new technology. A section in the course syllabus defining allowed and intended uses would provide easy access to such information Teachers using AI for grading or giving feedback, should clearly communicate to students the purpose and benefits. Communication of intent and expectation is paramount. When providing guidance for use of AI in an assignment/assessment, teachers need to consider carefully the course learning outcome(s) intended to be enhanced by a particular assignment. | S16: YM | T16: 46138 | U16: cy
A17: HK-013 | B17: Institutional | C17: Hong Kong | D17: HKU | E17: HKU | F17: Policy for AI in Education | G17: University Policy | I17: https://aied.talic.hku.hk/aipolicy/ | J17: Encouraging | K17: Not specified | L17: Instructor decides | M17: Equity | N17: Pedagogy/Learning | O17: Referenced to integrity code | P17: Both | Q17: Teachers and course coordinators need to consider if they will include and/or integrate GenAI into assessments and, if so, how to ensure assessments remain authentic and fair. academic integrity is an issue of concern for staff and students alike | S17: YM | T17: 46138 | U17: cy
A18: HK-014 | B18: Faculty/School | C18: Hong Kong | D18: HKU Faculty of Law | E18: HKU | F18: Guidelines on the Responsible Use of Generative AI in Research at The University of Hong Kong | G18: University Policy | I18: https://researchintegrity.law.hku.hk/guidelines-on-the-responsible-use-of-generative-ai-in-research-at-the-university-of-hong-kong/ | J18: Cautious | K18: Required | L18: Instructor decides | M18: Academic Integrity | N18: Privacy/Data/Ethics | O18: Guidance only | P18: Researchers | Q18: Use of GenAI for ideation and background research is only acceptable if... Students and assistants should seek approval from their supervisors on plans to use GenAI tools in the research process, and the usage should be well documented. Research students should also declare their use of GenAI tools and specify their usage at the time of thesis submission for examination. | S18: YM | T18: 46138 | U18: cy
A19: HK-015 | B19: Institutional | C19: Hong Kong | D19: HKU Research Services | E19: HKU | F19: Responsible Use of Generative AI in Research at HKU | G19: University Policy | I19: https://www.rss.hku.hk/integrity/generative-ai | J19: Cautious | K19: Required | L19: Instructor decides | M19: Academic Integrity | N19: Privacy/Data/Ethics | O19: Guidance only | P19: Researchers | Q19: Clearly disclose GenAI tool usage in research outputs, publications, or presentations, for example the type of GenAI used, data sources, and potential limitations. Maintain detailed documentation of GenAI prompts, outputs, and decision-making processes involving GenAI. | S19: YM | T19: 46138 | U19: cy
A20: HK-016 | B20: Course-wide | C20: Hong Kong | D20: HKU | E20: HKU | F20: Artificial Intelligence Literacy I (AILT1001) | G20: Syllabus | I20: https://ailt.cds.hku.hk/ | J20: Cautious | K20: Not specified | L20: Instructor decides | M20: Academic Integrity | N20: AI Literacy | O20: Explicit penalties | P20: Students only | Q20: Cheating: Such as copying or sharing answers, using unauthorized notes, online search engines, or AI tools including ChatGPT or Copilot in quizzes, tests, or other assessments without explicit permission. Any student found to have committed academic misconduct may receive a failing grade for the affected assessment or the course, be formally reported to the School and their home Faculty, and have a permanent record placed on file. Serious or repeated cases will be referred to the Vice-Chancellor for consideration by the University Disciplinary Committee, where penalties may include a published reprimand, suspension, or expulsion. | R20: It is a graduation requirement for undergrad students to pass this course. Course-wise, it is to promote AI Literacy. Policy-wise, the statement is to promote academic integrity. | S20: YM | T20: 46138 | U20: cy
A21: HK-017 | B21: Faculty/School | C21: Hong Kong | D21: HKU | E21: HKU | F21: Regulations and Syllabuses Bachelor of Journalism [BJ] | G21: Syllabus | I21: https://web.socsc.hku.hk/wp-content/uploads/2026/03/BJ_2025-26.pdf | J21: Functional | K21: Not specified | L21: Not specified | M21: AI Literacy | O21: None stated | P21: Students only | Q21: Artificial Intelligence Literacy Courses (6 credits) Candidates are required to complete 6 credits of artificial intelligence literacy, comprising two 3-credit microcredential courses: AILT1001. Artificial Intelligence Literacy I (3 credits) AILT9017. Digital Literacy Through a Social Sciences Lens* (3 credits)
A22: HK-018 | B22: Faculty/School | C22: Hong Kong | D22: HKU | E22: HKU | F22: Regulations and Syllabuses of the Double Degree of BEd and BSc | G22: Syllabus | I22: https://www4.hku.hk/pubunit/drcd/files/ugdr2025-26/Education/BEd&BSc.pdf | J22: Encouraging | K22: Not specified | L22: Faculty/Inst. decides | M22: AI Literacy | O22: Explicit penalties | P22: Students only | Q22: To complete the curriculum, candidates shall ... [complete] 6 credits in artificial intelligence literacy | R22: Establishes a graduation requirement but not a usage policy | S22: YM | T22: 46138 | U22: cy
A23: HK-019 | B23: Faculty/School | C23: Hong Kong | D23: HKU SPACE | E23: HKU | F23: Policy on Use of Generative Artificial Intelligence for Teaching and Learning | G23: University Policy | I23: https://hkuspace.hku.hk/news/detail/hku-policy-on-use-of-generative-artificial-intelligence-for-teaching-and-learning | J23: Functional | K23: Not specified | L23: Faculty/Inst. decides | M23: Academic Integrity | O23: Referenced to integrity code | P23: Both | Q23: Please note that HKU SPACE will follow the University’s policy as per previous announcements from the Deputy Director (Academic Services) on the School’s staff intranet. | R23: HKU Space is the self-financing "community colleges" associated with HKU. | S23: YM | T23: 46138 | U23: cy
A24: HK-020 | B24: Institutional | C24: Hong Kong | D24: HKU Teaching and Learning Innovation Centre | E24: HKU | F24: GenAI Use Cases Hub | G24: FAQ/Resource Page | I24: https://talic.hku.hk/innovation/ai-cop/hub/teaching-and-learning-application/ | J24: Encouraging | K24: Not specified | L24: Not specified | M24: Pedagogy/Learning | O24: None stated | P24: Both | Q24: GenAI Community of Practice (CoP) | R24: Repository of ways to use AI for teaching | S24: YM | T24: 46138 | U24: cy
A25: HK-021 | B25: Institutional | C25: Hong Kong | D25: Lingnan University | E25: Lingnan | F25: Lingnan’s big plan to advance data literacy | G25: Other | I25: https://www.ln.edu.hk/president/chatgpt/index.html | J25: Encouraging | K25: Conditional | L25: Instructor decides | M25: AI Literacy | O25: Guidance only | P25: Both | Q25: Lingnan faculty and students have to be AI literate they will be able to open up new dimensions in liberal arts education and ensure that each graduating class is multifaceted and future-ready. we have already purchased the licence for version 3.5 of ChatGPT for the whole university,” Qin says. “We will be training faculty and students to use it and are figuring out new ways to assess assignments and support learning The big plan to advance data literacy has also been developed to fully support the innovative adoption of generative AI tools in the teaching and learning environment of the University. professors will have to decide and specify when GPT can and can’t be used for written assignments. And there may be a new requirement for students to submit a list of the “prompts” they gave to get content used in coursework and essays. | S25: YM | T25: 46138 | U25: cy
A26: HK-022 | B26: Institutional | C26: Hong Kong | D26: Lingnan University - ITSC | E26: Lingnan | F26: Generative AI Service | G26: FAQ/Resource Page | I26: https://www.ln.edu.hk/itsc/services/teaching-learning-research-services/generative-ai-service | J26: Encouraging | K26: Not specified | L26: Not specified | M26: Pedagogy/Learning | O26: None stated | P26: Both | Q26: Lingnan University fully embraces the use of AI tools in support of its teaching and learning. | R26: ChatGPT service building on Microsoft’s Azure Open AI services in July 2023 | S26: YM | T26: 46138 | U26: cy
A27: HK-023 | B27: Institutional | C27: Hong Kong | D27: Lingnan University | E27: Lingnan | F27: Guidelines for Using Generative Artificial Intelligence (GAI) Tools at Lingnan University | G27: University Policy | H27: 45566 | I27: https://www.ln.edu.hk/tlc/f/page/107180/Guidelines%20for%20Using%20GAI%20Tools%20%28Oct%202024%29.pdf | J27: Encouraging | K27: Required | L27: Faculty/Inst. decides | M27: Academic Integrity | N27: Pedagogy/Learning | O27: Referenced to integrity code | P27: Both | Q27: While Lingnan University enthusiastically embraces innovative technologies in education, it firmly upholds the principle that students must adhere to rigorous standards of academic integrity in all forms of assessments. The following guidelines are designed to help faculty and students ethically integrate GAI tools into their teaching, learning, and assessment practices. Teaching staff can incorporate GAI into course design, learning activities, assignments, and assessments in line with outcome-based assessment, teaching, and learning principles, and the corresponding Qualifications Framework (QF) level. From Term 2, 2024-25, students are allowed to use GAI tools to assist them in preparing assignments, assessments, and other educational practices. However, teaching staff may still seek prior approval from the relevant Head of Department/Programme Director NOT to allow students to use GAI tools Teaching staff should inform students at the beginning of the course, in the syllabus, or in other written formats that GAI tools are not permitted (for use by students). All course syllabi should include an important note regarding the use of GAI tools as set out in the course syllabus template. | S27: YM | T27: 46137 | U27: cy
A28: HK-024 | B28: Institutional | C28: Hong Kong | D28: Lingnan University - Teaching and Learning Centre | E28: Lingnan | F28: Subject: Use of Generative Artificial Intelligence (GAI) Tools Term 1 2024-25 (Memo) | G28: Official Guidance | H28: 45513 | I28: https://www.ln.edu.hk/tlc/f/page/107180/Use%20of%20Generative%20Artificial%20Intelligence%20%28GAI%29%20Tools%20Term%201%202024-25.pdf | J28: Cautious | K28: Required | L28: Instructor decides | M28: Academic Integrity | N28: Equity | O28: Referenced to integrity code | P28: Both | Q28: In Term 1, 2024-25, teaching staff can choose to allow their students to use GAI tools to assist their preparation for assignments, assessments, and other educational practices. Teaching staff should communicate with students clearly about the use or not allowing the use of GAI tools through course outlines, syllabus, Moodle, or other written means of communication to prevent misunderstandings. Declaration If the use of GAI tools is allowed, students must declare the use of GAI tools or other Artificial Intelligence (AI) technology in their assignments and assessments using a sample template | R28: Compare this memo to the Lingnan course syllabi. The University may want to let instructors make their choices, but instructors' autonomy is not reflected in the course syllabi. | S28: YM | T28: 46137 | U28: EY
A29: HK-025 | B29: Faculty/School | C29: Hong Kong | D29: Lingnan University - Department of Translation | E29: Lingnan | F29: AI Usage Policy for UG and TPG Programmes | G29: University Policy | H29: 45673 | I29: https://www.ln.edu.hk/tran/f/page/116062/ai-usage-policy-for-ug-and-tpg-programmes.pdf | J29: Cautious | K29: Required | L29: Hybrid/Mixed | M29: Academic Integrity | O29: Explicit penalties | P29: Both | Q29: Lingnan students are allowed to use AI tools, but at the same time they need to follow the university’s academic and ethical guidelines. In line with the University Guidelines, students are expected to declare their usage of AI tools. It is agreed by the Department Board that the ceiling cap of AI usage is 40%.* If the AI detection rate is higher than this, marks will be deducted from students’ work because of lack of originality. Subject teachers have the discretion to impose a penalty for any AI usage higher than the cap rate. | R29: Department puts a more restrictive GenAI usage requirement and enforcement. | S29: YM | T29: 46137 | U29: EY
A30: HK-026 | B30: Course-wide | C30: Hong Kong | D30: Lingnan University - Department of English | E30: Lingnan | F30: ENG2101 | G30: Syllabus | I30: https://www.ln.edu.hk/eng/f/page/104051/ENG2101_AQAC_2024.pdf | J30: Functional | K30: Not specified | L30: Faculty/Inst. decides | M30: Academic Integrity | O30: Referenced to integrity code | P30: Students only | Q30: Students must adhere to the University’s guidelines and practices when using Generative Artificial Intelligence (AI) tools. The official documents “Guidelines for Using GAI Tools at Lingnan University” and “Best Practices for Ethical and Responsible Use of GAI Tools in Course Assessments” can be found here: https://www.ln.edu.hk/tlc/generativeartificialintelligence/gai-guidelines-best-practices. | R30: Holds for most other syllabi | S30: YM | T30: 46137 | U30: EY
A31: HK-027 | B31: Course-wide | C31: Hong Kong | D31: Lingnan University - Department of English | E31: Lingnan | F31: ENG3009 | G31: Syllabus | I31: https://www.ln.edu.hk/eng/f/page/104051/eng3009.pdf | J31: Functional | K31: Not specified | L31: Faculty/Inst. decides | M31: Academic Integrity | O31: Referenced to integrity code | P31: Students only | Q31: Students must adhere to the University’s guidelines and practices when using Generative Artificial Intelligence (AI) tools. The official documents “Guidelines for Using GAI Tools at Lingnan University” and “Best Practices for Ethical and Responsible Use of GAI Tools in Course Assessments” can be found here: https://www.ln.edu.hk/tlc/generativeartificialintelligence/gai-guidelines-best-practices. | R31: Holds for most other syllabi | S31: YM | T31: 46137
A32: HK-028 | B32: Course-wide | C32: Hong Kong | D32: Lingnan University - School of Data Science | E32: Lingnan | F32: CDS2002 | G32: Syllabus | I32: https://www.ln.edu.hk/sds/dai/ds/f/page/105561/CDS2002%20Introduction%20to%20Artificial%20Intelligence%20%28Required%29.190825.pdf | J32: Functional | K32: Not specified | L32: Faculty/Inst. decides | M32: Academic Integrity | O32: Referenced to integrity code | P32: Students only | Q32: Students must adhere to the University’s guidelines and practices when using Generative Artificial Intelligence (GAI) tools. The official documents “Guidelines for Using GAI Tools at Lingnan University” and “Best Practices for Ethical and Responsible Use of GAI Tools in Course Assessments” can be found here: https://www.ln.edu.hk/tlc/generative-artificial-intelligence/gai-guidelines-bestpractices . | R32: This is the Introduction to Artificial Intelligence course. The pedagogy focus may be AI Literacy, but the GenAI statement is clearly directed to Academic Integrity. | S32: YM | T32: 46137 | U32: EY
A33: HK-029 | B33: Institutional | C33: Hong Kong | D33: Lingnan University - Registry | E33: Lingnan | F33: Core Curriculum | G33: University Policy | I33: https://www.ln.edu.hk/reg/undergraduate-programmes/core-curriculum | J33: Encouraging | K33: Not specified | L33: Faculty/Inst. decides | M33: AI Literacy | O33: Explicit penalties | P33: Students only | Q33: Year 1 Intake students are assigned to take ... ‘CCC8015 Generative Artificial Intelligence’ in the first year Senior Year Intake students are assigned to take ... ‘CCC8015 Generative Artificial Intelligence’ in the third year. | R33: Graduation requirement | S33: YM | T33: 46138 | U33: EY
A34: HK-030 | B34: Institutional | C34: Hong Kong | D34: PolyU - Information Technology Services Office | E34: PolyU | F34: PolyU GenAI | G34: FAQ/Resource Page | I34: https://www.polyu.edu.hk/its/it-services/polyu-genai/ | J34: Functional | K34: Not specified | L34: Not specified | M34: Pedagogy/Learning | O34: None stated | P34: Both | Q34: The PolyU generative AI application is solely for PolyU staff and students to use for teaching and learning, research, and work-related activities only. | S34: YM | T34: 46138 | U34: EY
A35: HK-031 | B35: Institutional | C35: Hong Kong | D35: Hong Kong Polytechnic University (PolyU) | E35: PolyU | F35: Guidelines for Students on the Use of Generative Artificial Intelligence | G35: University Policy | H35: 46027 | I35: https://www.polyu.edu.hk/ar/docdrive/polyu-students/Student-guide-on-the-use-of-GenAI-revised-260105.pdf | J35: Functional | K35: Required | L35: Instructor decides | M35: Academic Integrity | O35: Referenced to integrity code | P35: Both | Q35: PolyU takes an open and forward-looking stance on the use of generative artificial intelligence (GenAI) tools (such as ChatGPT) as a positive and creative force in education, and the incorporation of such use in innovative learning, teaching, and assessment practices. In accordance with the above stance, the University emphasises that: • students are accountable for their own work; and • the use of GenAI (if permitted) in student work should be properly acknowledged. Some subjects and assessments may not allow or have restrictions on the use of GenAI tools. You may be required to declare the use of GenAI tools (e.g. by completing an honour declaration form) and identify the AI-generated content in your work. You should refer to the relevant subject and assessment documents for the specific restrictions and requirements. ... If in doubt, check with your teachers. Using Generative AI critically | ethical | wisely (DOs and DON'Ts) | S35: YM | T35: 46137 | U35: EY
A36: HK-032 | B36: Faculty/School | C36: Hong Kong | D36: PolyU - School of Design | E36: PolyU | F36: Generative AI Use Guideline & Design Research Integrity | G36: Official Guidance | H36: 45901 | I36: https://www.polyu.edu.hk/sd/-/media/department/sd/content/research-2/research-integrity/generative-ai-use-guideline--design-research-integrity202509.pdf | J36: Functional | K36: Required | L36: Instructor decides | M36: Academic Integrity | N36: AI Literacy | O36: Referenced to integrity code | P36: Researchers | Q36: PolyU is strongly committed to preserving academic integrity and has a zero-tolerance policy towards academic dishonesty. Do not commit such acts, e.g. cheating, contract cheating, plagiarism (copying others’ work as your own without full acknowledgement, including using generative artificial intelligence (GenAI) tools without proper referencing), impersonation, fabrication and falsification. THE SIX PRINCIPLES OF GenAI | S36: YM | T36: 46137 | U36: EY
A37: HK-033 | B37: Faculty/School | C37: Hong Kong | D37: PolyU - English Language Centre | E37: PolyU | F37: Brainstorming And Researching Ideas - The S.P.A.C.E. Framework | G37: Official Guidance | H37: 46021 | I37: https://www.polyu.edu.hk/elc/docdrive/genai_at_elc/GenAI@ELC_Brainstorming_and_Researching_Ideas.pdf | J37: Encouraging | K37: Required | L37: Faculty/Inst. decides | M37: Pedagogy/Learning | O37: Guidance only | P37: Students only | Q37: Leverage GenAI in the brainstorming and research process using the S.P.A.C.E. Framework To use GenAI purposefully and appropriately to facilitate personalised learning | R37: Example activity is taken from a Discipline Specific Requirement ELC subject. (Note: ELC is not a Faculty/School.) | S37: YM | T37: 46137 | U37: EY
A38: HK-034 | B38: Institutional | C38: Hong Kong | D38: PolyU Library | E38: PolyU | F38: Harnessing GenAI in Your Academic Journey: GenAI & Academic Integrity | G38: Library Guide | H38: 46128 | I38: https://libguides.lb.polyu.edu.hk/genai-academic/ai-academic-integrity | J38: Functional | K38: Required | L38: Instructor decides | M38: Academic Integrity | O38: Guidance only | P38: Students only | Q38: Review the policies and guidelines from your faculty, department, or subject. If anything is unclear, consult your course instructor to confirm whether the use of GenAI is permitted in your specific context. | R38: Library guide | S38: YM | T38: 46137 | U38: EY
A39: HK-035 | B39: Institutional | C39: Hong Kong | D39: PolyU EDC | E39: PolyU | F39: Explore a topic - Generative AI | G39: FAQ/Resource Page | I39: https://www.polyu.edu.hk/edc/explore-a-topic/generative-ai/ | J39: Encouraging | K39: Not specified | L39: Not specified | M39: Pedagogy/Learning | N39: AI Literacy | O39: Guidance only | P39: Both | Q39: Driven by a wish to harness the positives of GenAI tools, this section will act as a home for resources relating to how GenAI tools can be used in PolyU, and for links to guidelines to their usage by students and staff within the institution. | U39: EY
A40: HK-036 | B40: Course-wide | C40: Hong Kong | D40: PolyU | E40: PolyU | F40: Subject Description Form - SO2D01 | G40: Syllabus | H40: 45566 | I40: https://www.polyu.edu.hk/so/-/media/department/so/content/study/so2d01.pdf | J40: Functional | K40: Not specified | L40: Not specified | M40: Pedagogy/Learning | O40: None stated | P40: Students only | Q40: One of the Objectives: enhance students’ ability to learn-to-learn through self-reflection, peer assessment and exploration of relevant generative artificial intelligence and technological advances in assignments | R40: No AI policy in Subject Description Form | S40: YM | T40: 46137 | U40: EY
A41: HK-037 | B41: Course-wide | C41: Hong Kong | D41: PolyU | E41: PolyU | F41: FITE Case Study (1) - Redesigning and Implementing GenAI-ready Assessment | G41: Other | I41: https://www.polyu.edu.hk/edc/-/media/department/edc/content/explore-a-topic/generative-ai/fite-case-study---lydia.pdf | J41: Functional | K41: Required | L41: Instructor decides | M41: Pedagogy/Learning | N41: Privacy/Data/Ethics | O41: Referenced to integrity code | P41: Both | Q41: Students were encouraged to use different GenAI tools (e.g. ChatGPT, Scispace, Research Rabbit, Midjourney, Canva, Murf, etc.) in their group project. Clear guidelines and expectations on the use of GenAI tools, including acceptable usage and ethical concerns, were given to students. Students were asked to keep a log detailing how they have used GenAI in their project. They were also asked to reflect on the use of GenAI in their project work and submit the reflection (200–300 words) as a group. The reflection focused on how the use of GenAI helped them achieve the intended learning outcomes, the challenges they faced in using the technology (e.g. identifying inaccuracies) and why they chose one tool over another, etc. The assessment rubric for the group project was updated to evaluate how well students had accommodated the use of GenAI in an ethical, responsible, and effective manner. | R41: Not a policy comment, but explaining how the instructor redesigns learning to make good use of GenAI. | S41: YM | T41: 46137 | U41: EY
A42: HK-038 | B42: Faculty/School | C42: Hong Kong | D42: PolyU CPCE (including PolyU HKCC and SPEED) | E42: PolyU | F42: Student Handbook 2025/26 | G42: University Policy | H42: 46054 | I42: https://www.cpce-polyu.edu.hk/docs/cpceacademicregistrycarlibraries/default-document-library/cpce_student_handbook.pdf | J42: Cautious | K42: Required | L42: Faculty/Inst. decides | M42: Academic Integrity | O42: Explicit penalties | P42: Students only | Q42: Under "Cheating": Using unpermitted materials and aids [including Generative Artificial Intelligence (GenAI) if it is explicitly disallowed] during tests, examinations or other forms of assessment / assignment, be they in-person or online, or using materials / tools / aides (including GenAI) in impermissible ways to perform or complete an academic task Under "Avoid Plagiarism": Observe the rules and regulations about using Generative Artificial Intelligence (GenAI) tools set by your programme, and the subject that you are studying. | R42: HKCC shares the same Student Handbook (hence GenAI policies) with PolyU | S42: YM | T42: 46138 | U42: EY
A43: HK-039 | B43: Institutional | C43: Hong Kong | D43: PolyU | E43: PolyU | F43: Artificial Intelligence and Data Analytics Requirement | G43: University Policy | I43: https://www.polyu.edu.hk/cus/student/4-year-undergraduate-student/general-university-requirements/for-students-who-admitted-from-2022-23/artificial-intelligence-and-data-analytics-requirement/ | J43: Encouraging | K43: Not specified | L43: Faculty/Inst. decides | M43: AI Literacy | O43: Explicit penalties | P43: Students only | Q43: What you need to do: 4-Year Degree Students admitted in/after 2022/23 are required to complete a 2-credit for GUR-AIDA within the first year of studies. | R43: Graduation requirement | U43: EY
A44: HK-040 | B44: Institutional | C44: Hong Kong | D44: PolyU - Department of English and Communication | E44: PolyU | F44: Generative AI - Inappropriate usage and limitations | Department of English and Communication | G44: FAQ/Resource Page | I44: https://www.polyu.edu.hk/engl/experience-and-opportunities/generative-ai/inappropriate-usage-and-limitations/ | J44: Cautious | K44: Not specified | L44: Faculty/Inst. decides | M44: AI Literacy | O44: Referenced to integrity code | P44: Students only | Q44: ChatGPT bases its output on previous word patterns without regard to factual accuracy. Generative AI tools should not be relied on due to AI “hallucination”, which is text that appears convincing, but ultimately factually incorrect upon further checking. This has resulted in punishments for lawyers who used ChatGPT to cite cases that did not exist | R44: This is part of their website about GenAI use. This particular page lists improper use cases and examples. It links to PolyU's policies under "Other Resources".
A45: HK-041 | B45: Course-wide | C45: Hong Kong | D45: Lingnan University - Department of Philosophy | E45: Lingnan | F45: PHI1002 | G45: Syllabus | I45: https://www.ln.edu.hk/philoso/f/page/103887/PHI1002.pdf | J45: Not specified | K45: Not specified | L45: Faculty/Inst. decides | M45: Academic Integrity | O45: Referenced to integrity code | P45: Students only | Q45: Students shall be aware of the University regulations about dishonest practice in course... work, tests and examinations | R45: Not specific about AI. Holds for all other PHI (Department of Philosophy) Syllabi | S45: YM | T45: 46137 | U45: EY | V45: 1
A46: HK-042 | B46: Course-wide | C46: Hong Kong | D46: Lingnan University - Department of Philosophy | E46: Lingnan | F46: PHI2118 | G46: Syllabus | I46: https://www.ln.edu.hk/philoso/f/page/103887/PHI2118.pdf | J46: Not specified | K46: Not specified | L46: Faculty/Inst. decides | M46: Academic Integrity | O46: Referenced to integrity code | P46: Students only | Q46: Students shall be aware of the University regulations about dishonest practice in course... work, tests and examinations | R46: Course title is A Philosophical Introduction to Artificial Intelligence, but there is no AI usage policy statements! | S46: YM | T46: 46137 | U46: EY | V46: 1
A47: HK-043 | B47: Course-wide | C47: Hong Kong | D47: PolyU | E47: PolyU | F47: Subject Description Form - CE1002 | G47: Syllabus | I47: https://www.polyu.edu.hk/bre/docdrive/Subject_Syllabus/2025_26/ServiceLearning/CE1002.pdf | J47: Not specified | K47: Not specified | L47: Not specified | M47: AI Literacy | O47: None stated | P47: Students only | R47: This course teaches AI. No AI policy in Subject Description Form | S47: YM | T47: 46137 | U47: EY | V47: 1
A48: HK-044 | B48: Course-wide | C48: Hong Kong | D48: PolyU | E48: PolyU | F48: Subject Description Form - LGT1041 | G48: Syllabus | H48: 45505 | I48: http://www.lms.polyu.edu.hk/subject-syllabi/ug/LGT1041.pdf | J48: Not specified | K48: Not specified | L48: Not specified | M48: AI Literacy | O48: None stated | P48: Students only | R48: This course teaches AI. No AI policy in Subject Description Form | S48: YM | T48: 46137 | U48: EY | V48: 1
A49: HK-045 | B49: Course-wide | C49: Hong Kong | D49: PolyU | E49: PolyU | F49: Subject Description Form - EIE1D03 | G49: Syllabus | H49: 45901 | I49: https://www.polyu.edu.hk/eee/-/media/department/eee/content/study/subject-syllabi/eee-subject-syllabi/2024-10-ee-eie/eie1d03_sdf_2024.pdf | J49: Not specified | K49: Not specified | L49: Not specified | M49: AI Literacy | O49: None stated | P49: Students only | R49: This course teaches AI. No AI policy in Subject Description Form | S49: YM | T49: 46137 | U49: EY | V49: 1
A50: HK-046 | B50: Course-wide | C50: Hong Kong | D50: HKU | E50: HKU | F50: APAI1001 | G50: Syllabus | I50: https://webapp.science.hku.hk/sr4/servlet/enquiry?Type=Course&course_code=APAI1001 | J50: Not specified | K50: Not specified | L50: Not specified | M50: AI Literacy | O50: None stated | P50: Students only | R50: The syllabus teaches AI but doesn't state a GenAI usage policy | S50: YM | T50: 46138 | V50: 1
A51: HK-047 | B51: Course-wide | C51: Hong Kong | D51: PolyU | E51: PolyU | F51: AF1605 | G51: Syllabus | H51: 45870 | I51: https://www.polyu.edu.hk/af/-/media/department/af/content/study/subject-syllabi/ug/2025/af1605_20252.pdf | J51: Not specified | K51: Not specified | L51: Not specified | M51: Academic Integrity | O51: None stated | P51: Students only | R51: Nothing specific about AI | V51: 1
A52: HK-048 | B52: Course-wide | C52: Hong Kong | D52: PolyU | E52: PolyU | F52: MM4922 | G52: Syllabus | H52: 45497 | I52: https://www.polyu.edu.hk/mm/-/media/department/mm/content/study/subject-syllabi/mm4922.pdf | J52: Not specified | K52: Not specified | L52: Not specified | M52: Academic Integrity | O52: None stated | P52: Students only | R52: Nothing specific about AI | V52: 1

Sheet NEW_HK_Coding
A1: HK Coding — GenAI Policy Coding
A2: Fill one row per policy document. Use dropdowns wherever possible. See tab '5_Codebook' for definitions.
A4: ID | B4: Tier | C4: Region | D4: Jurisdiction / Institution | E4: Institution | F4: Document Title | G4: Document Type | H4: Publication Date | I4: Source URL | J4: Stance | K4: Disclosure | L4: Discretion | M4: Focus (Primary) | N4: Focus (Secondary) | O4: Enforcement | P4: Coverage | Q4: Key Quote (verbatim) | R4: Coder Notes | S4: Coder | T4: Date Coded | U4: Coder Agreement (Initials if agree and Comment if disagree)
A5: HK-001 | B5: National/Federal | C5: Hong Kong | F5: MOE sets 2026 priorities for digital education | G5: Official Guidance | H5: 46113 | I5: http://en.moe.gov.cn/news/press_releases/202604/t20260406_1432962.html | J5: Encouraging | K5: Not specified | L5: Gov-mandated | M5: Professional Readiness | N5: Pedagogy/Learning | O5: Guidance only | P5: Whole community | Q5: The MOE convened a meeting on March 31 to outline priorities for the next phase of the country’s digital education strategy, with a focus on integrating artificial intelligence (AI) across teaching, learning and educational management. Looking ahead, the meeting called for more systematic integration of AI across different areas of education. In schools, the focus will be on supporting personalized learning and equipping students with interdisciplinary skills relevant to emerging industries. In the field of lifelong learning, the meeting emphasized expanding digital platforms to better connect education with industry and society, with a view to improving the employability of graduates and supporting continuous skill development. | R5: This is an official press release article. It is included here because there is no equivalent "original text" available. We cannot say this 2026 March 31 meeting had any effect on the HK institutions just yet (too recent). But we can see the alignment across different Tiers. "Industry" seems to be very important in their framework. | S5: YM | V5: {=XLOOKUP($I5,TEST_HK_Coding!$I$5:$I$52,TEST_HK_Coding!$A$5:$A$52,"")}
A6: HK-002 | B6: National/Federal | C6: Hong Kong | F6: Ten major reforms shaping China’s education landscape in 2025 | G6: Official Guidance | H6: 46022 | I6: http://en.moe.gov.cn/news/press_releases/202601/t20260120_1427027.html | J6: Encouraging | K6: Not specified | L6: Gov-mandated | M6: Professional Readiness | O6: Guidance only | P6: Whole community | Q6: [Three of the ten "reform themes" mentioned AI] 3. Rebalancing university disciplines and degree programs - "New programs have been introduced in areas such as artificial intelligence..." 5. Training elite engineers for industries of strategic importance - "In fields such as semiconductors and artificial intelligence, universities and companies jointly recruit students, design curricula, supervise research, and share outcomes." 8. Expanding access to quality undergraduate education - "New places are concentrated in strategic fields such as artificial intelligence..." | R6: This is an official press release article. It is included here because there is no equivalent "original text" available. It summarizes the reform themes observed after MOE's "three-year action plan" and "a series of targeted reforms". AI is one of the country's major "Strategic fields". | S6: YM | V6: {=XLOOKUP($I6,TEST_HK_Coding!$I$5:$I$52,TEST_HK_Coding!$A$5:$A$52,"")}
A7: HK-003 | B7: National/Federal | C7: Hong Kong | F7: 教育部等五部门关于印发《“人工智能+教育”行动计划》的通知 | G7: Official Guidance | H7: 46122 | I7: https://www.nda.gov.cn/sjj/zwgk/zcfb/0413/20260410162428109058250_pc.html | J7: Encouraging | K7: Not specified | L7: Gov-mandated | M7: Professional Readiness | N7: AI Literacy | O7: Guidance only | P7: Whole community | Q7: （二）培育面向智能时代的高层次人才。推动人工智能成为高校公共基础课，按学科专业分类编写课程教材，推动全体学生掌握人工智能知识。根据人工智能技术特点，打造“短实新”的前沿创新课程。优化传统学科专业人才培养方案，指导高校开设人工智能交叉融合课程，丰富跨学科、跨专业课程群，培养复合型交叉人才。根据产业结构智能升级优化调整学科专业设置，新设一批适应新技术、新产业、新业态的学科专业。整合高水平研究型大学、科技领军企业、国家实验室等力量，深化学科交叉、产教融合、科教融汇，探索人工智能拔尖创新人才培养新模式。 (Google translate (verified): (II) Promote the integration of artificial intelligence (AI) as a core general education course within higher education institutions, developing specialized textbooks tailored to specific academic disciplines and majors to ensure that all students acquire a foundational understanding of AI. Drawing upon the unique characteristics of AI technology, develop cutting-edge, innovative courses that are concise, practical, and forward-looking. Optimize talent cultivation plans for traditional academic disciplines; guide universities in establishing interdisciplinary AI courses; enrich the array of cross-disciplinary and cross-major course clusters; and cultivate versatile, interdisciplinary talent. Adjust and optimize academic discipline and major offerings in alignment with the intelligent upgrading of industrial structures, establishing a new cohort of disciplines and majors designed to meet the demands of emerging technologies, industries, and business models. Integrate the resources of high-level research universities, leading technology enterprises, and national laboratories to deepen interdisciplinary convergence, industry-education integration, and science-education synergy, thereby exploring new models for cultivating top-tier, innovative talent in the field of artificial intelligence.) | R7: References two other documents (including HK-004): "根据《教育强国建设规划纲要（2024—2035年）》战略部署，按照《国务院关于深入实施“人工智能+”行动的意见》的要求，制定本计划。" For details, search for 高校 (= Higher Education Institutions) in the main text. Note that HK Inst. strictly speaking are not governed by these guidelines. | S7: YM | V7: {=XLOOKUP($I7,TEST_HK_Coding!$I$5:$I$52,TEST_HK_Coding!$A$5:$A$52,"")}
A8: HK-004 | B8: National/Federal | C8: Hong Kong | F8: 国务院关于深入实施“人工智能+”行动的意见 | G8: Official Guidance | H8: 45120 | I8: https://www.mee.gov.cn/zcwj/gwywj/202508/t20250827_1126207.shtml | J8: Encouraging | K8: Not specified | L8: Gov-mandated | M8: Pedagogy/Learning | N8: AI Literacy | O8: Guidance only | P8: Whole community | Q8: "推行更富成效的学习方式。把人工智能融入教育教学全要素、全过程，创新智能学伴、智能教师等人机协同教育教学新模式，推动育人从知识传授为重向能力提升为本转变，加快实现大规模因材施教，提高教育质量，促进教育公平。构建智能化情景交互学习模式，推动开展方式更灵活、资源更丰富的自主学习。鼓励和支持全民积极学习人工智能新知识、新技术。 (Promote more effective learning methods. Integrate artificial intelligence into every element and stage of education and instruction; pioneer new human-machine collaborative models—such as intelligent learning companions and AI teachers—to drive a shift in pedagogy from a primary focus on knowledge transmission to one centered on capability enhancement; accelerate the realization of personalized instruction on a large scale; improve educational quality; and foster educational equity. Establish intelligent, context-aware interactive learning models to facilitate self-directed learning characterized by greater flexibility and richer resources. Encourage and support the entire populace in actively acquiring new knowledge and technologies related to artificial intelligence.)" | R8: Referenced by HK-003. This is the first document in the list that takes Learning as the main focus (rather than Industry needs). | S8: YM | V8: {=XLOOKUP($I8,TEST_HK_Coding!$I$5:$I$52,TEST_HK_Coding!$A$5:$A$52,"")} -> HK-002
A9: HK-005 | B9: National/Federal | C9: Hong Kong | F9: Global AI Governance Action Plan | G9: Official Guidance | H9: 45864 | I9: https://hk.ocmfa.gov.cn/eng/xjpzxzywshd/202507/t20250729_11679232.htm | J9: Encouraging | K9: Not specified | L9: Gov-mandated | M9: Privacy/Data/Ethics | N9: Equity | O9: Guidance only | P9: Whole community | Q9: To this end, we hereby put forward the Global AI Governance Action Plan, calling on all parties to take concrete and effective actions in advancing global AI development and governance based on the objectives and principles of promoting AI for good and in service of humanity, respecting national sovereignty, aligning with development goals, ensuring safety and controllability, upholding fairness and inclusiveness, and fostering open cooperation. "Education" was mentioned under: 3. Advancing AI empowerment across industries. 9.Spearheading deployment and application by the public sector. 12.Strengthening international cooperation on AI capacity building. | R9: Another press release, which seems to be the only reference for this Action Plan? Mentions "AI+" (HK-004). | S9: YM | V9: {=XLOOKUP($I9,TEST_HK_Coding!$I$5:$I$52,TEST_HK_Coding!$A$5:$A$52,"")}
A10: HK-006 | B10: City/Territory | C10: Hong Kong | F10: The Chief Executives 2025 Policy Address Supplement | G10: Executive Order | H10: 45917 | I10: https://www.policyaddress.gov.hk/2025/public/pdf/supplement/supplement-full_en.pdf | J10: Encouraging | K10: Not specified | L10: Gov-mandated | M10: Pedagogy/Learning | N10: AI Literacy | O10: Guidance only | P10: Whole community | Q10: Promote digital education Collaborate with professional bodies to launch pilot schemes to promote AI education, including enhancement of professional training for teachers and strengthening the application of Generative AI in learning and teaching. (EDB) | R10: Grand direction | V10: {=XLOOKUP($I10,TEST_HK_Coding!$I$5:$I$52,TEST_HK_Coding!$A$5:$A$52,"")}
A11: HK-007 | B11: City/Territory | C11: Hong Kong | F11: The Chief Executive's 2024 Policy Address Education Bureau’s Policy Initiatives | G11: Executive Order | H11: 45597 | I11: https://www.edb.gov.hk/en/about-edb/legco/policy-address/2024_Panel_on_Education_Eng.pdf | J11: Encouraging | K11: Not specified | L11: Gov-mandated | M11: Pedagogy/Learning | N11: AI Literacy | O11: Guidance only | P11: Whole community | Q11: Setting up the Steering Committee on Strategic Development of Digital Education 16. To dovetail with the national development of digital education and to nurture talents for the innovation and technology (I&T) sector, the Government will continue to step up the promotion of STEAM education in primary and secondary schools, and enhance information technology in education to facilitate the deep integration of I&T, including artificial intelligence (AI), in education. We will set up the Steering Committee on Strategic Development of Digital Education in this school year to tender advice and suggestions on promoting digital education. [p.20] Under "Proposal on Launching the Research Matching Grant Scheme": mentioned "artificial intelligence" the Government proposes to launch the Scheme again in 2025 with $1.5 billion of matching grants to encourage the higher education sector to expand their research funding sources, and bolster support for the institutions’ academic research endeavours. The Scheme will cover four years from mid-2025 to mid-2029 | R11: Grand direction FIrst quote mostly directed to Primary and Secondary schools Money is spent | V11: {=XLOOKUP($I11,TEST_HK_Coding!$I$5:$I$52,TEST_HK_Coding!$A$5:$A$52,"")}
A12: HK-008 | B12: City/Territory | C12: Hong Kong | F12: Hong Kong Generative Artificial Intelligence Technical and Application Guideline | G12: Official Guidance | H12: 45992 | I12: https://www.digitalpolicy.gov.hk/en/our_work/data_governance/policies_standards/ethical_ai_framework/doc/HK_Generative_AI_Technical_and_Application_Guideline_en.pdf | J12: Encouraging | K12: Recommended | L12: Gov-mandated | M12: Privacy/Data/Ethics | N12: Equity | O12: Guidance only | P12: Whole community | Q12: Content Safety is a critical issue for generative AI services.Fabrication of Rumours refers to the challenge wherein generative AI services can produce highly convincing text, images, audio, video, and other multimedia content. education technology (EdTech) sector should ensure equitable access, preventing learning outcomes from being affected by algorithmic bias. Education: The education sector should regulate the use and scope of generative AI rather than outright banning students from using it. However, students should obtain teacher approval before using AI in their coursework, and AI-generated content should be clearly identifiable to prevent misuse that violates academic integrity. When teachers use generative AI in teaching, they must ensure that the generated content is truthful, accurate, and consistent in both textual and visual representation. If AI is used for grading assignments and exams, final results should always be reviewed by human educators. | R12: Their primary concern is the quality of the content and the threat it poses to society. This is very much within the realm of AI ethics | V12: {=XLOOKUP($I12,TEST_HK_Coding!$I$5:$I$52,TEST_HK_Coding!$A$5:$A$52,"")} -> HK-004
A13: HK-009 | B13: City/Territory | C13: Hong Kong | F13: Ethical Artificial Intelligence Framework | G13: Official Guidance | H13: 45992 | I13: https://www.digitalpolicy.gov.hk/en/our_work/data_governance/policies_standards/ethical_ai_framework/doc/Ethical_AI_Framework_en.pdf | J13: Encouraging | K13: Recommended | L13: Gov-mandated | M13: Privacy/Data/Ethics | N13: Equity | O13: Guidance only | P13: Whole community | Q13: balance AI innovation and development, application and responsibility, thereby constructing a governance framework with local characteristics that is suitable for Hong Kong's context Organisations can make use of the Ethical AI Framework when adopting AI and big data analytics in their IT projects or services. Ethical AI Framework is defined not only to serve as a reference/guide for the IT project team during the development and maintenance process. It also defines the governance structure to enable organisations to demonstrate accountability in building trust upon adoption of AI by evaluating the impact, ensuring safe and responsible use of AI and facilitating innovation. | R13: HongKong gov is basically saying: they have a good ai guidelines, please follow them, but they are not making them | V13: {=XLOOKUP($I13,TEST_HK_Coding!$I$5:$I$52,TEST_HK_Coding!$A$5:$A$52,"")} -> HK-003
A14: HK-010 | B14: City/Territory | C14: Hong Kong | F14: Fund for Innovative Technology-in-Education | G14: Official Guidance | H14: 45978 | I14: https://www.ugc.edu.hk/eng/ugc/activity/teach_learn/fite.html | J14: Encouraging | K14: Not specified | L14: Gov-mandated | M14: Pedagogy/Learning | N14: AI Literacy | O14: Guidance only | P14: Whole community | Q14: The UGC announced the launch of the Fund for Innovative Technology-in-Education (FITE) with a funding allocation of $100 million in June 2023 for 2023/24 – 2025/26 academic years, with $20 million earmarked for inter-institutional collaborative activities between institutions. The FITE aims to provide an impetus for universities to harness innovative and breakthrough technologies in transforming pedagogies and enriching student learning experiences, and to nurture a digitally competent and technologically responsible generation, for the future success of their students in the digital economy. | R14: $ | S14: YM | V14: {=XLOOKUP($I14,TEST_HK_Coding!$I$5:$I$52,TEST_HK_Coding!$A$5:$A$52,"")}
A15: HK-011 | B15: Institutional | C15: Hong Kong | E15: HKU | F15: Academic Integrity and University-wide Core Principles for Using AI in Teaching and Assessment | G15: Official Guidance | H15: 2026 | I15: https://talic.hku.hk/innovation/ai-ethics/core-principles/ | J15: Cautious | K15: Required | L15: Hybrid | M15: Academic Integrity | N15: Privacy/Data/Ethics | O15: Referenced to integrity code | P15: Students and Faculty | Q15: Staff and students are reminded that the HKU regulations and policies regarding plagiarism and academic mis-conduct supersede all other regulations, where there is a conflict, these regulations and policies take precedence. ANY misuse of AI or misrepresentation of AI work as one’s own independent creative work violates the HKU regulations as well as generally accepted principles of community, integrity and honor. Violations will be referred to the university disciplinary committee. Staff are reminded to draw students’ attention to this. With the advent of more sophisticated AI tools, it is essential that staff clearly explain to students the purpose of each assignment and/or assessment, and how this purpose has influenced their decisions about the extent to which use of AI is allowed/restricted instructors can decide how they wish to integrate AI in their academic practice; nonetheless, the core principles below provide guidance on current “best use”. | R15: Core principles School will provide a general guideline and faculty can lead their own rules on their own | V15: {=XLOOKUP($I15,TEST_HK_Coding!$I$5:$I$52,TEST_HK_Coding!$A$5:$A$52,"")} -> HK-012
A16: HK-012 | B16: Institutional | C16: Hong Kong | E16: HKU | F16: Policy for AI in Education | G16: Official Guidance | H16: ? | I16: https://aied.talic.hku.hk/aipolicy/ | J16: Encouraging | K16: Recommended | L16: Hybrid | M16: Equity | N16: Privacy/Data/Ethics | O16: Guidance only | P16: Students and Faculty | Q16: The six core principles to AI policy in education are: - equal access is important; - guaranteeing AI security is critical; - AI literacy is essential; - rethinking pedagogy is most likely necessary; - course assessment will be greatly impacted and may need to be redesigned; and - academic integrity is an issue of concern for staff and students alike. Assessment Teachers and course coordinators need to consider if they will include and/or integrate GenAI into assessments and, if so, how to ensure assessments remain authentic and fair. They must critically evaluate current assessment methods that may be susceptible to student use of GenAI and consider replacing them with alternatives. Integrity Students are accountable for all work they submit for assessments, including any content generated or used with the assistance of GenAI. The use of AI tools should be properly cited to state its contributions, alongside a declaration of how human judgment and oversight were exercised to achieve the final product. | R16: Many big keywords: Equity, Privacy/secutiry, AI Literacy, Pegagogy, Academic integrity | V16: {=XLOOKUP($I16,TEST_HK_Coding!$I$5:$I$52,TEST_HK_Coding!$A$5:$A$52,"")} -> HK-013
A17: HK-013 | B17: Institutional | C17: Hong Kong | E17: HKU | F17: Guidelines on the Responsible Use of Generative AI in Research at The University of Hong Kong | G17: Official Guidance | H17: 45908 | I17: https://www.rss.hku.hk/research-integrity/GenAI-research-guidelines.pdf | J17: Cautious | K17: Required | L17: Hybrid | M17: Academic Integrity | N17: Privacy/Data/Ethics | O17: Referenced to integrity code | P17: Researchers only | Q17: This document aims to provide general guidance on effective and responsible use of AI in research, especially in relation to the use of GenAI. The guidelines supplement and complement existing HKU policies, e.g. the Policy on Research Integrity (https://www.rss.hku.hk/integrity/rcr/policy) and Intellectual Property Rights Policy (https://www.rss.hku.hk/contracts/ipr), which should also be read and applied together with these guidelines. Use of GenAI for ideation and background research is only acceptable if • this specific usage of the GenAI system is duly documented and acknowledged; • the researcher has verified the accuracy, fairness, and originality (or lack of originality) of text, figures, table and data generated by a GenAI tool; • the researcher has verified that all relevant external primary sources are cited and represented fully and fairly; and • the use of GenAI does not inevitably disclose patentable inventions Students and assistants should seek approval from their supervisors on plans to use GenAI tools in the research process, and the usage should be well documented. Research students should also declare their use of GenAI tools and specify their usage at the time of thesis submission for examination. | R17: Built upon existing inst. policy. | S17: YM | V17: {=XLOOKUP($I17,TEST_HK_Coding!$I$5:$I$52,TEST_HK_Coding!$A$5:$A$52,"")}
A18: HK-014 | B18: Institutional | C18: Hong Kong | E18: HKU | F18: Responsible Use of Generative AI in Research at HKU | G18: Official Guidance | H18: 46156 | I18: https://www.rss.hku.hk/integrity/generative-ai | J18: Cautious | K18: Recommended | L18: Hybrid | M18: Academic Integrity | N18: Privacy/Data/Ethics | O18: Guidance only | P18: Students and Faculty | Q18: General Principles of Responsible Use 1. Research Integrity Avoid misleading information and ensure AI-generated content is accurate and do not violate research integrity principles, including fabrication, falsification, or misconduct. Be aware of potential biases in GenAI outputs and interpret results critically. 2. Data Validity and Quality Control Critically verify and interpret GenAI-generated content. Use human judgment and domain expertise to assess GenAI outputs. Do not rely solely on GenAI-generated content for research conclusions or publications. [There are several more points] Under "Best Practice": Document Usage: Keep detailed records of how and when GenAI tools are used in the research process. Notes This webpage aims to foster a culture of responsible and ethical use of GenAI in research, in alignment with HKU's overarching policies on research integrity and data management. It does not replace or supersede the standards set out in the Guidelines on the Responsible Use of Generative AI in Research at The University of Hong Kong. This webpage should also be read in conjunction with other institutional policies and regulations. | R18: They share a open mind for new ai tools and finding the right/postive method to accret with GENAI. | S18: cy | V18: {=XLOOKUP($I18,TEST_HK_Coding!$I$5:$I$52,TEST_HK_Coding!$A$5:$A$52,"")} -> HK-015
A19: HK-015 | B19: Institutional | C19: Hong Kong | E19: HKU | F19: Guidebook: Generative Artificial Intelligence for Teaching and Learning | G19: Official Guidance | H19: 2025 | I19: https://commoncore.hku.hk/wp-content/uploads/documents/Guidebook%20-%20GenAI%20in%20Teaching%20and%20Learning.pdf | J19: Encouraging | K19: Not specified | L19: Institution-mandated | M19: Pedagogy/Learning | N19: AI Literacy | O19: Guidance only | P19: Faculty only | Q19: The guidebook explores some of these capabilities, presents examples of thoughtful applications, and engages in dialogue about GenAI’s implementations and implications. By drawing on findings from the literature, alongside student and teacher interviews and case studies, this guidebook aims to provide teachers with the knowledge, frameworks, and practical strategies necessary to make informed decisions about GenAI use. Our hope is for teachers to use AI not merely to enhance existing models of learning but compose with it as a means to unsettle current paradigms and assumptions in higher education teaching and learning to flourish in more creative and impactful trajectories. | R19: Not strictly a "policy" document. But it contains different perspectives and use cases for faculty staff's pondering. | S19: YM | V19: {=XLOOKUP($I19,TEST_HK_Coding!$I$5:$I$52,TEST_HK_Coding!$A$5:$A$52,"")}
A20: HK-016 | B20: Faculty/Department | C20: Hong Kong | E20: HKU | F20: Using GenAI Responsibly in Your Research — A Quick Guide for RPG Students | G20: Official Guidance | H20: 45992 | I20: https://gradsch.hku.hk/news_and_events/newsletter/using-genai-responsibly-your-research-quick-guide-rpg-students | J20: Functional | K20: Required | L20: Hybrid | M20: Privacy/Data/Ethics | N20: Academic Integrity | O20: Referenced to integrity code | P20: Students and Faculty | Q20: Generative AI (GenAI) is transforming research by offering tools for idea generation, data processing, and content creation. However, its use introduces ethical, legal, and integrity challenges. Misuse can lead to plagiarism, data privacy breaches, and compromised research credibility. Understanding these risks ensures that GenAI is applied as a supportive tool—not a substitute for original thinking. For RPG supervisors - GenAI use should be deliberate to allow students to learn responsible research practices both with and without GenAI. - Supervisors should design tasks that include both GenAI-supported and GenAI-free activities. - The Graduate School, Faculties, Schools, Departments, and Centres should provide guidance and support to supervisors. For RPG students and trainees - Students and assistants must seek supervisor approval before using GenAI. - Disclosure of GenAI use is mandatory. - Usage should be well documented and meet the criteria for degree conferral (originality and contribution to knowledge). - Students must declare, and justify it when required, the use of GenAI at thesis submission. | R20: From Grad School. Most of the content is about how to use it responsibly. Points to HK-013 at the end. | S20: YM | V20: {=XLOOKUP($I20,TEST_HK_Coding!$I$5:$I$52,TEST_HK_Coding!$A$5:$A$52,"")}
A21: HK-017 | B21: Faculty/Department | C21: Hong Kong | E21: HKU | F21: HKU Policy on Use of Generative Artificial Intelligence for Teaching and Learning | G21: University Policy | H21: 45146 | I21: https://hkuspace.hku.hk/news/detail/hku-policy-on-use-of-generative-artificial-intelligence-for-teaching-and-learning | J21: Functional | K21: Not specified | L21: Institution-mandated | M21: Academic Integrity | O21: Referenced to integrity code | P21: Students and Faculty | Q21: Please note that HKU SPACE will follow the University’s policy as per previous announcements from the Deputy Director (Academic Services) on the School’s staff intranet. | R21: HKU Space is the self-financing "community colleges" associated with HKU. | S21: YM | V21: {=XLOOKUP($I21,TEST_HK_Coding!$I$5:$I$52,TEST_HK_Coding!$A$5:$A$52,"")} -> HK-019
A22: HK-018 | B22: Faculty/Department | C22: Hong Kong | E22: HKU | F22: Guidance for Using Generative AI Tools and Building Applications | G22: Official Guidance | H22: 2026 | I22: https://innowings.engg.hku.hk/innowing1/aiguide/ | J22: Encouraging | K22: Not specified | L22: Not specified | M22: Privacy/Data/Ethics | N22: Equity | O22: Referenced to integrity code | P22: Students only | Q22: Welcome to the world of generative AI and their versatile applications in building innovative solutions. These AI technologies offer powerful tools for creative problem-solving ideas and applications. However, their use must be accompanied by a strong commitment to ethical, responsible, and lawful practices. This document is intended to provide students with comprehensive guidelines for using generative AI tools and responsibly developing applications with them. [The first 3 guidelines] 1. Responsible AI: Crafting Ethical and Responsible Contents Generative AI tools empower us to create content. Use this power responsibly by ensuring that the generated content adheres to ethical and legal standards. Refrain from generating content that promotes harm, bias, discrimination, misinformation, or any form of unethical behavior. Test results/contents that may have embed such unethical behavior and avoid using them. Avoid any misuse of generative AI tools, including harassment, hate speech, plagiarism, or any illegal activities. 2. Limitation on created contents: Understanding the Limits of Generated Contents Recognize that user of AI-generated results/contents should bear the ultimate accountability in using them. Recognize the issues of confident responses produced by AI tools that are inaccurate or incoherent with the context, also known as hallucination, and the implications of prompt engineering in AI-generated results/contents. Consider whether AI-generated results/contents encourage or discourage diversity and conformity. 3. Data Protection: Safeguarding User Data Ensure that the data used with AI tools complies with the University’s privacy and data protection regulations (https://hku.hk/about/policies_reports/ privacy_policy.html). Do not collect any unnecessary personal data from users that is not relevant to the application’s functionality. Clearly inform individuals who utilize AI tools about the data to be collected and how the data will be used. Understand fully how personal data inputted to AI tools will be used beyond generating immediate results. Please seek approval from Human Research Ethics Committee (https://www.rss.hku.hk/integrity/ethics-compliance/hrec) before collecting any data for research purposes. | R22: This document is not written for teaching/learning in a course's context. The tone is like: AI is powerful! So use it with care. Focusing on Data. | S22: YM | V22: {=XLOOKUP($I22,TEST_HK_Coding!$I$5:$I$52,TEST_HK_Coding!$A$5:$A$52,"")}
A23: HK-019 | B23: Faculty/Department | C23: Hong Kong | E23: HKU | F23: Plagiarism Warning and Guidelines on Use of GenAI | G23: Official Guidance | H23: ? | I23: https://english.hku.hk/General_Information/Plagiarism_Warning_and_Guidelines_on_Use_of_GenAI | J23: Cautious | K23: Not specified | L23: Hybrid | M23: Academic Integrity | O23: Explicit penalties | P23: Students only | Q23: There are severe penalties for plagiarism in the School of English... POLICY on the use of generative artificial intelligence (genai) The University has prepared a policy document outlining the regulations that govern the use of generative artificial intelligence in teaching and learning. For details, please refer to the "Policy on Use of Generative Artificial Intelligence for Teaching and Learning" on the HKU Teaching and Learning website (requires HKU Portal Access). Final advice: In case of doubt, consult your teachers or tutors. | R23: Clearly point the "policy" to institutional but the decision to teachers | S23: YM | V23: {=XLOOKUP($I23,TEST_HK_Coding!$I$5:$I$52,TEST_HK_Coding!$A$5:$A$52,"")}
A24: HK-020 | B24: Faculty/Department | C24: Hong Kong | E24: HKU | F24: Generative AI Resource Hub | G24: FAQ/Resource Page | H24: 2026 | I24: https://www.med.hku.hk/en/teaching-and-learning/edtech/resource-hub | J24: Encouraging | K24: Required | L24: Institution-mandated | M24: AI Literacy | N24: Pedagogy/Learning | O24: Referenced to integrity code | P24: Students and Faculty | Q24: A collection of teaching materials and guidelines are being developed to facilitate the application of AI technologies in teaching and learning activities. Guidelines on the Use of Generative Artificial Intelligence in Teaching and Learning for Professional Degree Programmes [PDF] Generative AI literacy video series for HKUMed... | R24: The [PDF] is password protected. The video series is quite positive. | S24: YM | V24: {=XLOOKUP($I24,TEST_HK_Coding!$I$5:$I$52,TEST_HK_Coding!$A$5:$A$52,"")}
A25: HK-021 | B25: Course-wide | C25: Hong Kong | E25: HKU | F25: ICSS2026_Course Syllabus | G25: Syllabus | H25: 46014 | I25: https://summerinstitute.hku.hk/storage/media/Temp%20Files/2026_Course%20Outline/20251223_ICSS2026_Course%20Syllabus_2026-2 | J25: Functional | K25: Not specified | L25: Not specified | M25: Professional Readiness | O25: None stated | P25: Students only | Q25: Students will learn how to collect, process, and analyze large-scale digital and behavioral data using computational tools such as text analysis, network analysis, social media analytics, and LLMs. Emphasis will be placed on real-world applications in social scientific domains. | R25: LLM is one of the many tools covered in this course. No "specific AI policy" statements | S25: YM | V25: {=XLOOKUP($I25,TEST_HK_Coding!$I$5:$I$52,TEST_HK_Coding!$A$5:$A$52,"")}
A26: HK-022 | B26: Course-wide | C26: Hong Kong | E26: HKU | F26: PSYC7319 Course Syllabus | G26: Syllabus | H26: 2025 | I26: https://psychology.hku.hk/wp-content/programmes/MSocScPsy/CourseOutlines/7319.pdf | J26: Cautious | K26: Required | L26: Instructor decides | M26: Academic Integrity | N26: Pedagogy/Learning | O26: Explicit penalties | P26: Students only | Q26: (p.6) Generative AI usage The University provides students with access to GenAI tools. However, the GenAI tools, at least at this stage of development, should not be taken as reliable sources of knowledge for this course, for which the answers of GenAI tools to questions are too often (a) loaded with inaccuracies, (b) incomplete, and/or (c) misleadingly represented. Students who nonetheless choose to use any GenAI tools for completing their homework assignments should note that the same academic integrity standards are applicable for applying the tools as for other references. The application of GenAI, if any, in submitted work should be properly acknowledged. Submitting any GenAI output, in part or in whole, for homework assignments without explicit referencing (to indicate that the contents concerned are generated by the GenAI sources) will constitute plagiarism. AI tools, such as ChatGPT, DALL-E, and similar technologies, are ONLY permitted to help students, fine-tune assignments, or check grammar and writing style unless otherwise specified (see the table below). AI tools are NOT permitted to write the entire draft of a writing assignment, paragraphs, or sentences. You will receive a failed grade in the corresponding assessment if we suspect the content of your assignments is not written by you. It is essential to recognize that students bear responsibility for the content generated through AI queries, ensuring that it remains compliant with intellectual property laws, devoid of misinformation, plagiarism, and ethically sound. To maintain adherence to university policies on academic integrity, the utilization of AI tools must be acknowledged. Assignment/ Assessment Purpose of assignment/Assessment Acceptable use of AI tools Unacceptable use of AI tools Reasons for allowing/ restricting use of AI tools In-class group presentation and essay Exercise critical thinking and knowledge gained from the course to evaluate the chosen topic. Using AI tools for information gathering (finding theories and relevant research studies). Using AI tools for checking grammar. Using AI tools to generate the presentation slides or presentation scripts. Using AI tools to generate the outline or drafts of the essay. Students can use AI tools to enhance their information gathering. However, the main ideas and perspectives should come from the students’ own thinking. Public education article Encourage students to pay attention to societal needs, to consolidate and integrate knowledge learned from lectures, and to apply the learned knowledge to tackle realworld issues. Using AI tools for checking grammar. Using AI tools to generate any content ideas or to write the essay. This assignment requires the student to work on it independently. | R26: Statement starts with a big "However". The accepted and unaccepted uses are stated clearly with rationale with respect to assessment purpose. | S26: YM | V26: {=XLOOKUP($I26,TEST_HK_Coding!$I$5:$I$52,TEST_HK_Coding!$A$5:$A$52,"")}
A27: HK-023 | B27: Course-wide | C27: Hong Kong | E27: HKU | F27: PSYC7315 Course Syllabus | G27: Syllabus | H27: 2024 | I27: https://psychology.hku.hk/wp-content/programmes/MSocScPsy/CourseOutlines/7315.pdf | J27: Cautious | K27: Required | L27: Instructor decides | M27: Academic Integrity | N27: Pedagogy/Learning | O27: Explicit penalties | P27: Students only | Q27: The University provides students with access to GenAI tools. However, their application is (a) not necessary for learning the contents of this course and (b) not expected to be advantageous for completing the course’s assignments. The GenAI tools, at least at this stage of development, should not be taken as reliable sources of knowledge for this course, for which the answers of GenAI tools to questions are too often (a) loaded with inaccuracies, (b) incomplete, and/or (c) misleadingly represented. Students who nonetheless choose to use any GenAI tools for completing their homework assignments should note that the same academic integrity standards are applicable for applying the tools as for other references. The application of GenAI, if any, in submitted work should be properly acknowledged. Submitting any GenAI output, in part or in whole, for homework assignments without explicit referencing (to indicate that the contents concerned are generated by the GenAI sources) will constitute plagiarism. | R27: There is a separate section for "Plagiarism" detailing the penalties. | S27: YM | V27: {=XLOOKUP($I27,TEST_HK_Coding!$I$5:$I$52,TEST_HK_Coding!$A$5:$A$52,"")}
A28: HK-024 | B28: Course-wide | C28: Hong Kong | E28: HKU | F28: UPAD7001 Course Syllabus | G28: Syllabus | H28: 2025 | I28: https://foa-media.arch.hku.hk/media/upload/2025/10/UPAD7001_Reseach_Design_Seminar_Series_Course-Outline_2025-2026_10Sep.pdf | J28: Functional | K28: Required | L28: Instructor decides | M28: Academic Integrity | O28: Explicit penalties | P28: Students only | Q28: Generative AI (GAI) – 1. Students are expected to do their assignments themselves and not asking someone else or Generative AI to do it for them. 2. The use of GAI needs to be properly declared. The declaration should include but not limited to which tool(s) and version are used at what stage and for what purposes as well as whether GAI generated texts have been further digested and rewritten by students in their assignments. 3. As an English medium university, we are expecting our students to be able to submit their assignments in their own written English and not translated by someone else, the computer, or Generative AI. 4. Assignments not done by the students themselves may result in grade penalties and constitute academic misconduct. Students are advised to consult and confirm with course teachers regarding permitted uses of GAI for individual courses and assignments. | R28: Looks like a generic statement, e.g. "consult and confirm with course teachers... for individual courses and assignments". But this document is a syllabus of a single course - UPAD7001 Research Design Seminar Series. Using AI = Asking someone else "MAY result in penalties" | S28: YM | V28: {=XLOOKUP($I28,TEST_HK_Coding!$I$5:$I$52,TEST_HK_Coding!$A$5:$A$52,"")}
A29: HK-025 | B29: Course-wide | C29: Hong Kong | E29: HKU | F29: GEOG3422 Course Syllabus | G29: Syllabus | H29: 2025 | I29: https://bpyloo.hku.hk/wp-content/uploads/2025/09/GEOG3422-Course-Outline-01Sep2025.pdf | J29: Cautious | K29: Required | L29: Instructor decides | M29: Academic Integrity | O29: Explicit penalties | P29: Students only | Q29: The course instructor and the course TA will check the originality report prior to marking. We view breaches of copyright and plagiarism, as well as the improper use of GenAI, very seriously. • When the detected AI percentage surpass the threshold of 30%, course teachers will provide the relevant students with the AI detection reports, and ask them to explain the process whereby they arrived at the submitted assignment, accompanied with any supporting documents (e.g. initial drafts, sources of data, and references read). • When grading the assignments with AI detection rate over the threshold, the teachers will consider the AI detection report (including which part of the writing is flagged) together with the student explanation. • Plagiarized work or work with improper use of AI will receive a fail grade. There may also be disciplinary action against the student who commits the above offence. | R29: It is explicit that one ot the reason of using Turnitin is the detection of improper AI use (bigger than 30%). All negative. No mention of how GenAI may be useful. Almost Prohibitive, but still, 30% is 30%. | S29: YM | V29: {=XLOOKUP($I29,TEST_HK_Coding!$I$5:$I$52,TEST_HK_Coding!$A$5:$A$52,"")}
A30: HK-026 | B30: Institutional | C30: Hong Kong | E30: PolyU | F30: Guidelines for Students on the Use of Generative Artificial Intelligence | G30: Official Guidance | H30: 46023 | I30: https://www.polyu.edu.hk/ar/docdrive/polyu-students/Student-guide-on-the-use-of-GenAI-revised-260105.pdf | J30: Encouraging | K30: Conditional | L30: Hybrid | M30: Academic Integrity | N30: Privacy/Data/Ethics | O30: Referenced to integrity code | P30: Students only | Q30: PolyU takes an open and forward-looking stance on the use of GenAI tools as a positive and creative force in education... While embracing the use of new technology in education, PolyU upholds the principle that students must adhere to high standards of academic integrity... The Student Code of Conduct and the policy on academic integrity apply to the use of GenAI in student work. In accordance with the above stance, the University emphasises that: • students are accountable for their own work; and • the use of GenAI (if permitted) in student work should be properly acknowledged. Some subjects and assessments may not allow or have restrictions on the use of GenAI tools. You may be required to declare the use of GenAI tools (e.g. by completing an honour declaration form) and identify the AI-generated content in your work. You should refer to the relevant subject and assessment documents for the specific restrictions and requirements. ... If in doubt, check with your teachers. Using Generative AI critically | ethical | wisely (DOs and DON'Ts) | R30: There is no need for new rules; simply integrate GenAI into the existing academic integrity framework,which is findinga comermise ground between ai tools and guidelines | S30: cy | U30: YM (added something) | V30: {=XLOOKUP($I30,TEST_HK_Coding!$I$5:$I$52,TEST_HK_Coding!$A$5:$A$52,"")} -> HK-031
A31: HK-027 | B31: Institutional | C31: Hong Kong | D31: PolyU Edcuation Development Centre | E31: PolyU | F31: Generative AI | G31: FAQ/Resource Page | H31: 2026 | I31: https://www.polyu.edu.hk/edc/explore-a-topic/generative-ai/ | J31: Encouraging | K31: Not specified | L31: Instructor decides | M31: Pedagogy/Learning | N31: Academic Integrity | O31: Guidance only | P31: Students and Faculty | Q31: It is expected that the usage of generative AI will become a normal part of learning, teaching, and assessment from 2023/24 Semester One. attempting to stop their usage seems likely to fail and be counterproductive. Driven by a wish to harness the positives of GenAI tools, this section will act as a home for resources relating to how GenAI tools can be used in PolyU, and for links to guidelines to their usage by students and staff within the institution. | R31: Leveraging GenAi& Redesigning assessment seems the best way to adapt AI streaming,it's a teaching opportunity to seize | S31: cy | U31: YM | V31: {=XLOOKUP($I31,TEST_HK_Coding!$I$5:$I$52,TEST_HK_Coding!$A$5:$A$52,"")} -> HK-035
A32: HK-028 | B32: Institutional | C32: Hong Kong | E32: PolyU | F32: Honour Declaration for Individual Assessment/Assignment | G32: Other | H32: ? | I32: https://www.polyu.edu.hk/edc/-/media/department/edc/content/explore-a-topic/academic-integrity/expanded-honour-declaration-forms_june-2024.pdf?la=en&hash=EBAD20FDCE2877034F7943181F8793AC | J32: Functional | K32: Required | L32: Hybrid | M32: Academic Integrity | N32: Pedagogy/Learning | O32: Explicit penalties | P32: Students only | Q32: I have read, understood and followed the requirements of this subject and, in particular, the requirements related to using GenAI in this assessment/assignment.The work in this assessment/assignment is my own work. No part of this assessment/assignment is taken from other people’s work and/or other sources, including GenAI output, without giving them credit through proper referencing. All references have been clearly cited in the convention snd format appropriate for this assessment/assignment. (...) Students who are found committing academic dishonesty will face disciplinary actions. Penalties may include reduced grades, failed subjects, and suspension and expulsion from the University. | V32: {=XLOOKUP($I32,TEST_HK_Coding!$I$5:$I$52,TEST_HK_Coding!$A$5:$A$52,"")}
A33: HK-029 | B33: Institutional | C33: Hong Kong | E33: PolyU | F33: Student Handbook for Taught Programmes 2025/26 | G33: Official Guidance | H33: 46143 | I33: https://www.polyu.edu.hk/ar/docdrive/polyu-students/student-handbook/Student_Handbook_2025-26_English.pdf | J33: Functional | K33: Required | L33: Instructor decides | M33: Pedagogy/Learning | N33: Academic Integrity | O33: Explicit penalties | P33: Students only | Q33: Cheating: Using unpermitted materials and aids (including Generative Artificial Intelligence (GenAI) if it is explicitly disallowed), during tests, examinations, or other forms of assessment/assignment, be they in-person or online, or using materials/tools/aides (including GenAI) in impermissible ways to perform or complete an academic task Observe the rules and regulations about using Generative Artificial Intelligence (GenAI) tools set by your Department, programme, and the subject that you are studying. | V33: {=XLOOKUP($I33,TEST_HK_Coding!$I$5:$I$52,TEST_HK_Coding!$A$5:$A$52,"")}
A34: HK-030 | B34: Institutional | C34: Hong Kong | D34: PolyU Academic Registry | E34: PolyU | F34: Must-read for success in your study | G34: Official Guidance | H34: 45926 | I34: https://www.polyu.edu.hk/ar/students-in-taught-programmes/notices-to-students/2025/2025-09-26_must-read-for-success-in-your-study/ | J34: Cautious | K34: Required | L34: Institution-mandated | M34: Academic Integrity | O34: Explicit penalties | P34: Students only | Q34: PolyU is strongly committed to preserving academic integrity and has a zero-tolerance policy towards academic dishonesty. Do not commit such acts, e.g. cheating, contract cheating (paying a 3rd party to complete your work), plagiarism (copying others’ work as your own without full acknowledgement, including using generative artificial intelligence (GenAI) tools without proper referencing), impersonation, fabrication and falsification. | R34: Quite serious wording: "Do not act in a way that you will regret later." | U34: YM | V34: {=XLOOKUP($I34,TEST_HK_Coding!$I$5:$I$52,TEST_HK_Coding!$A$5:$A$52,"")}
A35: HK-031 | B35: Faculty/Department | C35: Hong Kong | D35: PolyU Design | E35: PolyU | F35: Research Integrity | G35: Official Guidance | H35: 2026 | I35: https://www.polyu.edu.hk/sd/research/research-integrity/ | J35: Functional | K35: Required | L35: Institution-mandated | M35: Academic Integrity | N35: AI Literacy | O35: Guidance only | P35: Students and Faculty | Q35: These guidelines are designed to help colleagues and students at the School of Design use GenAI responsibly, transparently, and ethically. It aligns with university policies while addressing the specific contexts and challenges faced by designers. | R35: The Full Guides PDF are both restricted by a login page | U35: YM | V35: {=XLOOKUP($I35,TEST_HK_Coding!$I$5:$I$52,TEST_HK_Coding!$A$5:$A$52,"")}
A36: HK-032 | B36: Faculty/Department | C36: Hong Kong | D36: PolyU English Learning Centre | E36: PolyU | F36: GenAI@ELC | G36: FAQ/Resource Page | H36: 2026 | I36: https://www.polyu.edu.hk/elc/genai/ | J36: Encouraging | K36: Recommended | L36: Institution-mandated | M36: AI Literacy | N36: Academic Integrity | O36: Referenced to integrity code | P36: Students and Faculty | Q36: PolyU takes an open and forward-looking stance on the use of generative artificial intelligence (GenAI) tools as a positive and creative force in education, and encourages the incorporation of such use in innovative learning, teaching, and assessment practices. While embracing the use of new technology in education, PolyU upholds the principle that students must adhere to high standards of academic integrity in all forms of assessments, and should be accountable for their own work. Academic dishonesty includes misrepresenting AI-generated work as one’s own. | R36: A big resource hub for "learning and teaching" | U36: YM | V36: {=XLOOKUP($I36,TEST_HK_Coding!$I$5:$I$52,TEST_HK_Coding!$A$5:$A$52,"")}
A37: HK-033 | B37: Faculty/Department | C37: Hong Kong | D37: PolyU English Learning Centre | E37: PolyU | F37: Using AI to improve your Language Skills (Teacher Version) | G37: FAQ/Resource Page | H37: 45791 | I37: https://www.polyu.edu.hk/elc/docdrive/genai_at_elc/Using_AI_to_improve_your_Language_Skills_Teacher_Version.pdf | J37: Functional | K37: Required | L37: Instructor decides | M37: Pedagogy/Learning | N37: Academic Integrity | O37: Explicit penalties | P37: Faculty only | Q37: The ELC follows the PolyU policy with regard to the use of GenAI tools. In summary, students are accountable for their own work. You should always refer to Student Information Sheets and ask your teacher to check when you may use GenAI tools in this subject. Relying too much on AI can mean that you do not meet the assessment requirements. This will lead to either a low grade or fail grade for an assessment. | R37: "Teacher Version" | U37: YM | V37: {=XLOOKUP($I37,TEST_HK_Coding!$I$5:$I$52,TEST_HK_Coding!$A$5:$A$52,"")}
A38: HK-034 | B38: Faculty/Department | C38: Hong Kong | D38: PolyU School of Design | E38: PolyU | F38: Generative AI Use Guideline & Design Research Integrity | G38: Official Guidance | H38: 45901 | I38: https://www.polyu.edu.hk/sd/-/media/department/sd/content/research-2/research-integrity/generative-ai-use-guideline--design-research-integrity202509.pdf | J38: Functional | K38: Required | L38: Institution-mandated | M38: Academic Integrity | N38: AI Literacy | O38: Referenced to integrity code | P38: Students only | Q38: PolyU is strongly committed to preserving academic integrity and has a zero-tolerance policy towards academic dishonesty. Do not commit such acts, e.g. cheating, contract cheating, plagiarism (copying others’ work as your own without full acknowledgement, including using generative artificial intelligence (GenAI) tools without proper referencing), impersonation, fabrication and falsification. So… | R38: The slides begin with "What is Research Integrity" | U38: YM | V38: {=XLOOKUP($I38,TEST_HK_Coding!$I$5:$I$52,TEST_HK_Coding!$A$5:$A$52,"")} -> HK-032
A39: HK-035 | B39: Faculty/Department | C39: Hong Kong | D39: PolyU Department of English and Communication | E39: PolyU | F39: Generative AI - Inappropriate usage and limitations | Department of English and Communication | G39: FAQ/Resource Page | H39: 2026 | I39: https://www.polyu.edu.hk/engl/experience-and-opportunities/generative-ai/inappropriate-usage-and-limitations/ | J39: Cautious | K39: Required | L39: Not specified | M39: AI Literacy | N39: Pedagogy/Learning | O39: Referenced to integrity code | P39: Students only | Q39: ChatGPT bases its output on previous word patterns without regard to factual accuracy. Generative AI tools should not be relied on due to AI “hallucination”, which is text that appears convincing, but ultimately factually incorrect upon further checking. This has resulted in punishments for lawyers who used ChatGPT to cite cases that did not exist: | R39: This is part of their website about GenAI use. This particular page lists improper use cases and examples. It links to PolyU's policies under "Other Resources". | S39: cy | U39: YM | V39: {=XLOOKUP($I39,TEST_HK_Coding!$I$5:$I$52,TEST_HK_Coding!$A$5:$A$52,"")} -> HK-040
A40: HK-036 | B40: Course-wide | C40: Hong Kong | D40: PolyU Department of Building and Real Estate | E40: PolyU | F40: BRE506 (from Programme Requirement Document) | G40: Syllabus | H40: 45536 | I40: https://www.polyu.edu.hk/bre/docdrive/32111-32112-32113_BRE_AY24-25.pdf | J40: Functional | K40: Required | L40: Instructor decides | M40: Academic Integrity | N40: Pedagogy/Learning | O40: Referenced to integrity code | P40: Students only | Q40: If students intend to use Generative AI (GenAI) tools for brainstorming or generating initial ideas, literature search or writing of group assignment reports, they are required to declare the use of such tools (e.g. ChatGPT, Poe, Google Bard, Microsoft Bing AI, etc) in preparing their submitted work, and where and how they have been used, in the preface of their group report and to submit their interactive chat history file including the writing prompts with the AI chatbots as written evidence in students’ work without plagiarism. If students have adopted AI-generated texts or materials in their work, they must properly cite and reference them in accordance with accepted academic conventions and citation styles. Students may refer to the Guidelines for Students on the Use of Generative Artificial Intelligence (source: https://www.polyu.edu.hk/ar/students-in-taught-programmes/use-of-genai) developed by the Academic Registry (AR) of PolyU for reference. | R40: Same note for BRE581. Quite neutral. No penalties mentioned but also no encouraging tone. Just use it with disclosure. | S40: YM | V40: {=XLOOKUP($I40,TEST_HK_Coding!$I$5:$I$52,TEST_HK_Coding!$A$5:$A$52,"")}
A41: HK-037 | B41: Course-wide | C41: Hong Kong | D41: PolyU Department of Building and Real Estate | E41: PolyU | F41: BRE533 (from Programme Requirement Document) | G41: Syllabus | H41: 45536 | I41: https://www.polyu.edu.hk/bre/docdrive/32111-32112-32113_BRE_AY24-25.pdf | J41: Encouraging | K41: Not specified | L41: Instructor decides | M41: Pedagogy/Learning | N41: Academic Integrity | O41: None stated | P41: Students only | Q41: The generative AI tools (genAI) is not allowed for (1) functions identification and function analysis; (2) generating creativity ideas during Value Management workshop but encouraged for (1) search for typical examples or cases of value management (2) helping improve structure, grammar, writing, presentation slides, etc. | R41: A bit more positive than HK-036 (from the same department). "Encouraged" for searching and writing. No requirement or consequences stated. | S41: YM | V41: {=XLOOKUP($I42,TEST_HK_Coding!$I$5:$I$52,TEST_HK_Coding!$A$5:$A$52,"")}
A42: HK-038 | B42: Course-wide | C42: Hong Kong | E42: PolyU | F42: ENGL5037 | G42: Syllabus | H42: 45444 | I42: https://www.polyu.edu.hk/engl/-/media/department/engl/content/study/full-subject-list/level-5-subjects/engl5037_20241_v062024.pdf?rev=4b025a9c057a4610ae7412df21ff9f4c&hash=8D2390F6F57D0EBFBD4658D32FC64610 | J42: Functional | K42: Not specified | L42: Not specified | M42: Professional Readiness | N42: Privacy/Data/Ethics | O42: None stated | P42: Students only | Q42: ILOs: Upon completion of the subject, students will be able to: a. Identify key affordances and limitations related to generative AI and its usage as an analytical tool. b. Showcase proficiency in using generative AI as an analytical tool in various professional contexts. c. Identify key affordances and limitations of generative AI as a content generator and as a communicative tool. d. Showcase proficiency in using generative AI as a contentgenerating tool. e. Understand the various forms of bias inherent in, and the relevant concerns with, AI-generated responses. f. Use generative AI appropriate for creative problemsolving. | R42: GenAI is the focus of the course. The course talks about "affordances and limitations", i.e. what AI can or cannot do as a tool. No "specific AI policy" stated. | S42: YM | V42: {=XLOOKUP($I43,TEST_HK_Coding!$I$5:$I$52,TEST_HK_Coding!$A$5:$A$52,"")}
A43: HK-039 | B43: Course-wide | C43: Hong Kong | E43: PolyU | F43: MM6452 | G43: Syllabus | H43: 45383 | I43: https://www.polyu.edu.hk/mm/-/media/department/mm/content/study/subject-syllabi_tpg/mm6452.pdf | J43: Functional | K43: Not specified | L43: Not specified | M43: Professional Readiness | N43: AI Literacy | O43: None stated | P43: Students only | Q43: Individual AI content design: The individual AI content design assesses students' comprehension of various aspects, including Generative AI models, multi-mode AI content generation, and the application and evaluation of AI content in different business scenarios. | R43: A very "applied" course on GenAI. No "specific AI policy" stated. | S43: YM | V43: {=XLOOKUP($I44,TEST_HK_Coding!$I$5:$I$52,TEST_HK_Coding!$A$5:$A$52,"")}
A44: HK-040 | B44: Course-wide | C44: Hong Kong | E44: PolyU | F44: COMP5571 | G44: Syllabus | H44: 45870 | I44: https://www.polyu.edu.hk/comp/docdrive/tpg/subject/COMP5571.pdf | J44: Functional | K44: Not specified | L44: Not specified | M44: Professional Readiness | N44: Privacy/Data/Ethics | O44: None stated | P44: Students only | Q44: The subject is envisioned for students to embrace and leverage the potential of Generative Artificial Intelligence (AI). It will primarily focus on the nature, development, and implications of Generative AI, its role in innovative research methods, its application across various disciplines, and its ethical and societal implications. | R44: A very "applied" course on GenAI. No "specific AI policy" stated. | S44: YM | V44: {=XLOOKUP(I44,TEST_HK_Coding!$I$5:$I$52,TEST_HK_Coding!$A$5:$A$52,"")}
A45: HK-041 | B45: Institutional | C45: Hong Kong | E45: Lingnan | F45: Guidelines for Using Generative Artificial Intelligence (GAI) Tools at Lingnan University | G45: University Policy | H45: 45566 | I45: https://www.ln.edu.hk/tlc/f/page/107180/Guidelines%20for%20Using%20GAI%20Tools%20%28Oct%202024%29.pdf | J45: Cautious | K45: Required | L45: Institution-mandated | M45: Pedagogy/Learning | N45: AI Literacy | O45: Guidance only | P45: Students and Faculty | Q45: "While Lingnan University enthusiastically embraces innovative technologies in education, it firmly upholds the principle that students must adhere to rigorous standards of academic integrity in all forms of assessments." "From Term 2, 2024-25, students are allowed to use GAI tools to assist them in preparing assignments, assessments, and other educational practices." | R45: teachers can turn it off for their course, students must declare every use, and academic integrity rules still run the show | S45: cy | V45: {=XLOOKUP($I45,TEST_HK_Coding!$I$5:$I$52,TEST_HK_Coding!$A$5:$A$52,"")} -> HK-023
A46: HK-042 | B46: Institutional | C46: Hong Kong | E46: Lingnan | F46: Best Practices for Ethical and Responsible Use of Generative Artificial Intelligence (GAI) Tools in Course Assessments | G46: Official Guidance | H46: 45870 | I46: https://www.ln.edu.hk/tlc/f/page/107180/Best%20Practices%20for%20Ethicial%20and%20Responsibilities%20Use%20of%20GAI%20%28Aug%202025%29.pdf | J46: Encouraging | K46: Required | L46: Hybrid | M46: Academic Integrity | N46: Privacy/Data/Ethics | O46: Referenced to integrity code | P46: Students and Faculty | Q46: To enhance the overall learning experience for our students, Lingnan University has decided to allow the use of ChatGPT and other GAI tools from the 2023-24 academic year. However, users should use these tools responsibly and ethically, and fully understand their potential and limitations. Upholding academic integrity is of utmost importance to all students. This document outlines the principles, practices, and actions that teaching staff and students need to be aware of/take regarding the implications of using GAI tools in course assessments. Students are encouraged to consult with their teaching staff if they have any questions. Course Assignment and Assessment (Open book) - Unless otherwise specified by the teaching staff, GAI tools are allowed to be used by students. Course Assessment (Closed book) & Final Examination (Closed book) - Unless otherwise specified by teaching staff, GAI tools are allowed to be used by students. Students should declare their use of GAI tools and reflect on the process. Students should indicate which GAI tools they have used and explain how the materials generated have been incorporated into their submitted work. | R46: The default is: Students are allowed to use GenAI tools. It is repeated multiple times in the full text. | S46: YM | V46: {=XLOOKUP($I46,TEST_HK_Coding!$I$5:$I$52,TEST_HK_Coding!$A$5:$A$52,"")}
A47: HK-043 | B47: Institutional | C47: Hong Kong | E47: Lingnan | F47: Use of Generative Artificial Intelligence (GAI) Tools Term 1 2024-25 | G47: University Policy | H47: 45513 | I47: https://www.ln.edu.hk/tlc/f/page/107180/Use%20of%20Generative%20Artificial%20Intelligence%20%28GAI%29%20Tools%20Term%201%202024-25.pdf | J47: Cautious | K47: Required | L47: Instructor decides | M47: Academic Integrity | N47: Privacy/Data/Ethics | O47: Referenced to integrity code | P47: Faculty only | Q47: In Term 1, 2024-25, teaching staff can choose to allow their students to use GAI tools to assist their preparation for assignments, assessments, and other educational practices. Teaching staff should communicate with students clearly about the use or not allowing the use of GAI tools through course outlines, syllabus, Moodle, or other written means of communication to prevent misunderstandings. Declaration If the use of GAI tools is allowed, students must declare the use of GAI tools or other Artificial Intelligence (AI) technology in their assignments and assessments using a sample template | R47: The first line is "Dear colleagues" Term 1: The teacher decides whether to allow it or not. Term 2: The university plans to make it universally allowed - teachers should adapt to it in advance. | S47: cy | U47: YM | V47: {=XLOOKUP($I47,TEST_HK_Coding!$I$5:$I$52,TEST_HK_Coding!$A$5:$A$52,"")} -> HK-024
A48: HK-044 | B48: Institutional | C48: Hong Kong | D48: Lingnan U Teaching and Learning Centre | E48: Lingnan | F48: Generative Artificial Intelligence | G48: FAQ/Resource Page | H48: 2026 | I48: https://www.ln.edu.hk/tlc/generative-artificial-intelligence | J48: Functional | K48: Not specified | L48: Institution-mandated | M48: Privacy/Data/Ethics | N48: AI Literacy | O48: Referenced to integrity code | P48: Students and Faculty | Q48: Disclaimer: Please be aware that artificial intelligence tools may reflect biases present in the data used to train them. These biases can influence the responses provided, potentially leading to incomplete, inaccurate, or skewed information. Always verify critical information from multiple reliable sources and use your judgment when interpreting AI-generated content. When using open platform AI tools, please ensure adherence to Lingnan University Information Security Data Governance and Protection, and Data Privacy Policy. For detailed information, please refer to: Data Governance and Protection; Data Privacy and Protection for Lingnan University | R48: A resource page for both students and staff. Disclaimer is a very small part of the whole page/site. | S48: YM | V48: {=XLOOKUP($I48,TEST_HK_Coding!$I$5:$I$52,TEST_HK_Coding!$A$5:$A$52,"")}
A49: HK-045 | B49: Institutional | C49: Hong Kong | D49: Lingnan U Academic Quality Assurance Manual | E49: Lingnan | F49: Chapter 4 - Quality Assurance and Enhancement of Student Assessment | G49: FAQ/Resource Page | H49: 2026 | I49: https://www.ln.edu.hk/main/aqa/table-of-contents/chapter-four | J49: Encouraging | K49: Not specified | L49: Hybrid | M49: Pedagogy/Learning | N49: Academic Integrity | O49: None stated | P49: Students and Faculty | Q49: To enhance the overall learning experience for students, the University has decided to allow the use of ChatGPT and other Generative AI tools from the 2023-24 academic year. In July 2023, the Teaching and Learning Centre issued the “Best Practices for Ethical and Responsible Use of Generative Artificial Intelligence (GAI) Tools in Course Assessments” which outline the principles, practices, and actions that need to be aware of/taken by course instructors and students regarding the implications of using GAI tools in course assessments. In October 2024, the Senate approved the updated “Best Practices for Ethical and Responsible Use of GAI Tools in Course Assessment” (Appendix I) and the “Guidelines for Using GAI Tools at Lingnan University” (Appendix J) effective from Term 2 of the 2024-25 academic year. Students are allowed to use GAI tools to assist them in preparing assignments, assessments, and other educational practices, provided these tools are used ethically and responsibly, in accordance with the GAI Guidelines. However, teaching staff may still seek prior approval from the relevant Head of Department/Programme Director NOT to allow students to use GAI tools (in part or their entirety) to prepare assignments, assessments, and other educational practices. | R49: This is NOT the UGC Audit report. From the preface: "Bringing together all the policies, regulations and guidelines pertaining to the assurance and enhancement of academic quality, it is easily available to all relevant staff and students." The Institutional stance is Encouraging, but teachers can seek approval NOT to allow students to use GenAI. "Head of Department/Programme Director" has the final say. | S49: YM | V49: {=XLOOKUP($I49,TEST_HK_Coding!$I$5:$I$52,TEST_HK_Coding!$A$5:$A$52,"")}
A50: HK-046 | B50: Faculty/Department | C50: Hong Kong | D50: Lingnan University Department of Translation | E50: Lingnan | F50: AI Usage Policy for UG and TPG Programmes | G50: University Policy | H50: 45673 | I50: https://www.ln.edu.hk/tran/f/page/116062/ai-usage-policy-for-ug-and-tpg-programmes.pdf | J50: Cautious | K50: Recommended | L50: Hybrid | M50: Academic Integrity | O50: Explicit penalties | P50: Students and Faculty | Q50: Starting from Term 2 of the 2024-25 academic year, Lingnan students are allowed to use AI tools, but at the same time they need to follow the university's academic and ethical guidelines. It is agreed by the Department Board that the ceiling cap of AI usage is 40%.* If the AI detection rate is higher than this, marks will be deducted from students’ work because of lack of originality. Subject teachers have the discretion to impose a penalty for any AI usage higher than the cap rate. Faculty members of the Department of Translation are expected to reiterate the University Guidelines and the Departmental Policy on AI usage to students, while students, both at BA and MA levels, should follow the University Guidelines and Departmental Policy on AI usage carefully | R50: Conditional permission with hard numerical limits and total disclosure — a translation department's pragmatic answer to a tool that can do its students' homework | S50: cy | U50: YM | V50: {=XLOOKUP($I50,TEST_HK_Coding!$I$5:$I$52,TEST_HK_Coding!$A$5:$A$52,"")} -> HK-025
A51: HK-047 | B51: Faculty/Department | C51: Hong Kong | D51: Lingnan University Department of Translation | E51: Lingnan | F51: AI Enabled Tools Declaration Form | G51: Other | H51: 45922 | I51: https://view.officeapps.live.com/op/view.aspx?src=https%3A%2F%2Fwww.ln.edu.hk%2Ftran%2Ff%2Fpage%2F116062%2FAI%2520Enabled%2520Tools%2520Declaration%2520Form_Translation_20250922.docx&wdOrigin=BROWSELINK | J51: Functional | K51: Required | L51: Faculty/Dept decides | M51: Academic Integrity | O51: Referenced to integrity code | P51: Students only | R51: This Declaration Form points back to the Institutional Guidelines (HK-041) and Best Practices (HK-042). | S51: YM | V51: {=XLOOKUP($I51,TEST_HK_Coding!$I$5:$I$52,TEST_HK_Coding!$A$5:$A$52,"")}
A52: HK-048 | B52: Faculty/Department | C52: Hong Kong | D52: Lingnan U School of Graduate Studies | E52: Lingnan | F52: GUIDEBOOK FOR RESEARCH POSTGRADUATE STUDENTS | G52: Official Guidance | H52: 45931 | I52: https://www.ln.edu.hk/sgs/f/upload/114745/Guidebook_for_RPg_Students.pdf | J52: Cautious | K52: Required | L52: Institution-mandated | M52: Academic Integrity | O52: Referenced to integrity code | P52: Students only | Q52: "It is agreed by the Department Board that the ceiling cap of AI usage is 40%. If the AI detection rate is higher than this, marks will be deducted from students' work because of lack of originality." | R52: This is a guidebook from the Grad School. GAI is mentioned under "Academic Honesty". | S52: YM | V52: {=XLOOKUP($I52,TEST_HK_Coding!$I$5:$I$52,TEST_HK_Coding!$A$5:$A$52,"")}
A53: HK-049 | B53: Faculty/Department | C53: Hong Kong | D53: Lingnan U Centre for English and Additional Languages | E53: Lingnan | F53: Use of Generative AI in Assessed Work | G53: University Policy | H53: ? | I53: https://www.ln.edu.hk/ceal/f/page/109859/CEAL%20Gen%20AI%20Policy%20for%20students.pdf | J53: Cautious | K53: Required | L53: Faculty/Dept decides | M53: Academic Integrity | O53: Explicit penalties | P53: Students only | Q53: If there is a question over the inappropriate use of GenAI (“authorship”) we will carry out an investigation. If you are found to, on the balance of probabilities, have used Gen AI inappropriately, you will be asked to rewrite and resubmit. There will also be a cap on your grade. For the first time this happens your essay grade will be capped at 60%. The second time the cap will be 40%. The third time will be raised as a case of academic misconduct to the exam board. Please note that records will be kept across all LUE courses. This means that if you submit inappropriate work in LUE1001, and then again in 4001, this will be seen as the second incidence. You should keep a portfolio of your work (called the “work in progress folder”), including screenshots of interactions with GenAI, drafts, plans and anything you do in preparation for the assessment. You will submit all of this as a zip file alongside the essay. This will not be assessed and there is no penalty for non-submission. However, if there is a question over the authorship of your essay this can be taken into account. If you are suspected of using AI inappropriately, the following will happen. - We will arrange a time to have a meeting. There will be two members of staff in this meeting, and you can also bring a friend. This friend can give moral support and also help with language, if needed - We will ask you questions about your essay and the process of writing it. We will also give you a chance to explain anything that you think is important. (Please note that not having enough time is not a reasonable explanation). - We will then send you an email with our decision. | R53: Pretty negative. | S53: YM | V53: {=XLOOKUP($I53,TEST_HK_Coding!$I$5:$I$52,TEST_HK_Coding!$A$5:$A$52,"")}
A54: HK-050 | B54: Faculty/Department | C54: Hong Kong | D54: Lingnan University Department of History | E54: Lingnan | F54: Guidelines for Using Generative Artificial Intelligence (GAI) Tools | G54: University Policy | H54: ? | I54: https://www.ln.edu.hk/history/f/upload/105794/345198/HIST%20Departmental%20policy%20on%20GAI%20tools.pdf | J54: Functional | K54: Required | L54: Hybrid | M54: Pedagogy/Learning | N54: Academic Integrity | O54: Referenced to integrity code | P54: Students and Faculty | Q54: Starting Term 2, 2024-25, students are permitted to use GAI tools, including editing and spellchecking tools such as Grammarly and DeepL, to assist with their course assignments, provided they adhere to the University’s guidelines. In line with the University’s best practices for the use of GAI tools, our department has developed additional guidelines. Students must declare the use of GAI tools, specifying which GAI tools they used and how they utilized them for their assignments. Examples of GAI usage include brainstorming ideas, generating reference lists, and editing. Sample Declaration: [cut] Students should include this declaration in their assignment. Meanwhile, faculty members must remind students of the University Guidelines and the Departmental Policy on using GAI tools. | R54: Built upon the institutional rules. Starts with how GenAI can be helpful in their work. ("permitted", not encouraged/welcome) Mentions both students and faculty members. | S54: YM | V54: {=XLOOKUP($I54,TEST_HK_Coding!$I$5:$I$52,TEST_HK_Coding!$A$5:$A$52,"")}
A55: HK-051 | B55: Course-wide | C55: Hong Kong | E55: Lingnan | F55: CDS2002 Course Syllabus | G55: Syllabus | H55: ? | I55: https://www.ln.edu.hk/sds/dai/ds/f/page/105561/CDS2002%20Introduction%20to%20Artificial%20Intelligence%20%28Required%29.190825.pdf | J55: Functional | K55: Not specified | L55: Institution-mandated | M55: Academic Integrity | N55: Professional Readiness | O55: Referenced to integrity code | P55: Students only | Q55: Students must adhere to the University’s guidelines and practices when using Generative Artificial Intelligence (GAI) tools. The official documents “Guidelines for Using GAI Tools at Lingnan University” and “Best Practices for Ethical and Responsible Use of GAI Tools in Course Assessments” can be found here: https://www.ln.edu.hk/tlc/generative-artificial-intelligence/gai-guidelines-bestpractices . | R55: This "Intro to AI" course uses the standard template: https://tlc.ln.edu.hk/SyllabusTool/ Course content is quite hardcore. Lots of advanced Computer Science stuff, not just everyday literacy. | S55: YM | V55: {=XLOOKUP($I55,TEST_HK_Coding!$I$5:$I$52,TEST_HK_Coding!$A$5:$A$52,"")} -> HK-028
A56: HK-052 | B56: Course-wide | C56: Hong Kong | E56: Lingnan | F56: CDS3003 Course Syllabus | G56: Syllabus | H56: ? | I56: https://www.ln.edu.hk/sds/dai/ds/f/page/105561/CDS3003%20Machine%20Learning%20%28Required%29.190825.pdf | J56: Functional | K56: Not specified | L56: Institution-mandated | M56: Academic Integrity | N56: Professional Readiness | O56: Referenced to integrity code | P56: Students only | Q56: Students must adhere to the University’s guidelines and practices when using Generative Artificial Intelligence (GAI) tools. The official documents “Guidelines for Using GAI Tools at Lingnan University” and “Best Practices for Ethical and Responsible Use of GAI Tools in Course Assessments” can be found here: https://www.ln.edu.hk/tlc/generative-artificial-intelligence/gai-guidelines-bestpractices . | R56: This "Machine Learning" course uses the standard template: https://tlc.ln.edu.hk/SyllabusTool/ Course content is quite hardcore. Lots of advanced Computer Science stuff, not just everyday literacy. | S56: YM | V56: {=XLOOKUP($I56,TEST_HK_Coding!$I$5:$I$52,TEST_HK_Coding!$A$5:$A$52,"")}
A57: HK-053 | B57: Course-wide | C57: Hong Kong | D57: Lingnan U Faculty of Business | E57: Lingnan | F57: Master of Science in Artificial Intelligence and Business Analytics Student Handbook | G57: Syllabus | H57: 2023? | I57: https://www.ln.edu.hk/sds/dai/mscaiba/f/page/72803/MScAIBA%20-%20Student%20Handbook%202023-24.pdf | J57: Functional | K57: Not specified | L57: Institution-mandated | M57: Academic Integrity | N57: Privacy/Data/Ethics | O57: Referenced to integrity code | P57: Students only | Q57: 7.2.1 Use of Advanced Technologies To support the University's strategy on use of advanced technologies such as ChatGPT and other generative AI tools to facilitate learning, ITSC launched the ChatGPT service that is built on Microsoft's Open AI services. Users should agree to the terms and conditions to ensure that tool is used appropriately and effectively while adhering to strict academic integrity standards. Details of the terms and conditions: https://chatgpt.In.edu.hk/. Please also refer to the the Best Practices for Ethical and Responsible Use of Generative Artificial Intelligence (AI) Tools in Course Assessments on TLC's website: https://www.ln.edu.hk/f/upload/84485/AI%20Practice_updated%2024%20Jul%202023_final.pdf | R57: This Master Programme document directs readers to (an earlier version of) the Institutional Best Practice document (HK-042). | S57: YM | V57: {=XLOOKUP($I57,TEST_HK_Coding!$I$5:$I$52,TEST_HK_Coding!$A$5:$A$52,"")}
A58: HK-054 | B58: Course-wide | C58: Hong Kong | E58: Lingnan | F58: SPA1302 Course Syllabus | G58: Syllabus | H58: ? | I58: https://www.ln.edu.hk/ceal/f/page/109868/SPA1302.pdf | J58: Cautious | K58: Not specified | L58: Faculty/Dept decides | M58: Pedagogy/Learning | N58: Academic Integrity | O58: Explicit penalties | P58: Students only | Q58: (5) Students must adhere to the University’s guidelines and practices when using Generative Artificial Intelligence (AI) tools. The official documents “Guidelines for Using GAI Tools at Lingnan University” and “Best Practices for Ethical and Responsible Use of GAI Tools in Course Assessments” can be found here: https://www.ln.edu.hk/tlc/generative-artificial-intelligence/gaiguidelines-best-practices. Use of Generative AI At CEAL we adopt a forward thinking and pragmatic approach to the use of Generative AI by students. Each assessment will carry guidelines about what type of AI use is acceptable. If you cannot find these, or if they are unclear, please ask your teacher. If there is a question over the inappropriate use of GenAI (“authorship”) we will carry out an investigation. If you are found to, on the balance of probabilities, have used Gen AI inappropriately, you will be asked to rewrite and resubmit. There will also be a cap on your grade More information can be found at: CEAL Gen AI Policy for students.pdf | R58: In addition to the template message, the CEAL adoption (HK-049) is mentioned. Each assessment will have its specific GenAI guidelines. It is phrased as if students are expected to use GenAI, but we cannot be sure unless we see the actual assessments. If we read HK-049, the requirements and penalties are pretty harsh. But those are not mentioned in this syllabus document. | S58: YM | V58: {=XLOOKUP($I58,TEST_HK_Coding!$I$5:$I$52,TEST_HK_Coding!$A$5:$A$52,"")}
A59: HK-055 | B59: Course-wide | C59: Hong Kong | E59: Lingnan | F59: CCC8013 Course Syllabus | G59: Syllabus | H59: ? | I59: https://www.ln.edu.hk/dos/f/upload/109663/CCC8013%20The%20Process%20of%20Science%20-%20Revised%20Syllabus%20%20Rubrics_20240807.pdf | J59: Encouraging | K59: Required | L59: Instructor decides | M59: Academic Integrity | N59: Pedagogy/Learning | O59: None stated | P59: Students only | Q59: 5. Students are allowed to employ AI-enabled tools in their course assignments of Tech Report and Group Presentation. Declaration of the use of Generative AI tools and the explanation how the generated materials have been incorporated into the assignments should be included in the submitted assignments. Besides, students should reference the Generative AI generated materials in their work with accepted academic conventions | R59: This is a rare case where the statement details what students are allowed to do with AI. Does NOT use the standard template. Consequences are not mentioned. | S59: YM | V59: {=XLOOKUP($I59,TEST_HK_Coding!$I$5:$I$52,TEST_HK_Coding!$A$5:$A$52,"")}

Sheet Updated_Codebook
A1: Codebook
A3: Tier
A4: Option | B4: Definition | C4: Example
A5: National/Federal | B5: Issued by a central government body with country-wide authority. NYC = US federal bodies; HK = PRC central government bodies. | C5: Central government policy (U.S. federal / China national).
A6: City/ Territory | B6: Issued by a subnational government body below national level but above any single institution. NYC = New York State and NYC bodies; HK = HKSAR government bodies. | C6: Subnational government policy (New York State / HKSAR, EDB, UGC).
A7: Institutional | B7: Issued by a university-wide body. Applies to all members of that institution regardless of faculty or department. | C7: University-wide policy (e.g. Columbia, HKU).
A8: Faculty/Department | B8: Issued by a sub-unit of a university. Applies only within that school, faculty, or department. | C8: Guidelines set by Faculty or Department.
A9: Course-wide | B9: Issued by an individual instructor. Applies only to enrolled students in a single course for a specific term. | C9: Individual course syllabus or instructor-set rule.
A12: Stance
A13: Option | B13: Definition | C13: Example
A14: Prohibitive | B14: Explicitly bans GenAI use. | C14: "strictly prohibited," "not permitted," "banned," "do not use," "prohibited in this class"
A15: Cautious | B15: Allows use but imposes conditions (permission / disclosure / citation). | C15: "use with caution," "risks must be considered," "only with permission," "be aware of limitations," "potential for misuse"
A16: Functional | B16: Use is accepted or recognized as a tool (like a calculator), focused on the use of AI and its function rather than whether is good or bad | C16: "may be used," "is permitted," "cite as you would any source," "use responsibly," "tools are available"
A17: Encouraging | B17: Use is promoted as a benefit to learning or a partner, | C17: "encouraged," "harness the potential," "embrace," "AI-powered," "empowering," "reap the benefits"
A19: Disclosure
A20: Option | B20: Definition | C20: Example
A21: Required | B21: Students must cite, acknowledge, or declare GenAI use. | C21: "must," "shall," "required to"
A22: Recommended | B22: Disclosure is suggested but not required. | C22: "should," "encouraged to"
A23: Conditional | B23: Required only for specific tasks (e.g., more than 10% text). | C23: "if you use AI, you must..."
A24: Not specified | B24: No statement about disclosure.
A26: Discretion
A27: Option | B27: Definition | C27: Example
A28: Government-mandated | B28: Issued by a government body external to the university
A29: Institution mandated | B29: Issued by a university-wide body (provost, senate, registry)
A30: Faculty/Dept decides | B30: Issued by a sub-unit of the university (school, department)
A31: Instructor decides | B31: Each instructor sets the rule at the course level. Individual course syllabus or instructor statement
A32: Hybrid | B32: The institution establishes a baseline policy (floor) that all must follow, while explicitly delegating additional or more specific rules to faculty or instructors at the course level. Both levels of governance are active simultaneously.
A33: Not specified | B33: Resource guide with no enforceable rule.
A36: Focus
A37: Option | B37: Definition | C37: Example
A38: Academic Integrity | B38: Primary concern is cheating, plagiarism, authorship, citation, or whether student work reflects the student’s own understanding. | C38: “Use of AI without disclosure will be treated as academic dishonesty.”
A39: AI Literacy | B39: Primary concern is effective, critical, ethical, and responsible AI use, including understanding AI’s limits, biases, errors, and appropriate applications. | C39: “Students will learn how to evaluate AI outputs and use GenAI responsibly.”
A40: Privacy/Data/ Ethics | B40: Primary concern is data protection, FERPA, confidentiality, cybersecurity, or avoiding the input of personal, sensitive, or institutional data into AI tools. | C40: “Do not enter confidential, personal, or student data into public AI tools.”
A41: Equity | B41: Primary concern is fair access, bias, discrimination, accessibility, or unequal effects across student groups. | C41: “AI tools should be used in ways that do not disadvantage students with limited access or produce biased outcomes.”
A42: Pedagogy/Learning | B42: Primary concern is teaching, learning, assessment design, student thinking, feedback, creativity, or how AI affects the learning process. | C42: “AI may be used for brainstorming, outlining, or feedback, but students remain responsible for their learning.”
A43: Professional Readiness | B43: Primary concern is preparing students, faculty, workers, or institutions for AI-related skills needed in future careers, research, or society. | C43: “Students should learn to use AI tools because they are increasingly part of professional practice.”
A46: Enforcement
A47: Option | B47: Definition | C47: Example
A48: Explicit penalties | B48: A specific consequence for non-compliance is named directly in the document. The reader does not need to consult another document to understand what happens if they violate the rule. | C48: "will be considered academic misconduct," "marks will be deducted," "failing grade," "strictly prohibited… violations"
A49: Referenced to integrity code | B49: No penalty is stated directly. The document points to an existing integrity policy or university regulation where consequences are defined. | C49: "in accordance with the university's academic integrity policy," "subject to disciplinary action under," "refer to the student handbook"
A50: Guidance only | B50: Recommendations or best practices with no connection to a penalty or integrity code. Non-compliance carries no stated formal consequence. | C50: "we recommend," "should consider," "best practice," "encouraged to," "guidance is designed to help"
A51: None stated | B51: The document addresses GenAI but contains no reference to enforcement, penalties, integrity codes, or compliance of any kind. Includes purely descriptive, resource-based, or aspirational documents.
A54: Coverage
A55: Option | B55: Definition | C55: Example
A56: Students only | B56: The document addresses student behavior and obligations exclusively. Instructors appear only as enforcers, not as a governed audience. | C56: "students are required," "students must," "student use of," "student submissions"
